[
  {
    "id": "bitcoin",
    "symbol": "btc",
    "name": "Bitcoin",
    "image": "https://assets.coingecko.com/coins/images/1/large/bitcoin.png?1696501400",
    "current_price": 70770,
    "market_cap": 1392444275089,
    "market_cap_rank": 1,
    "fully_diluted_valuation": 1486989851393,
    "total_volume": 47121993496,
    "high_24h": 71419,
    "low_24h": 66811,
    "price_change_24h": 3884.22,
    "price_change_percentage_24h": 5.80722,
    "market_cap_change_24h": 76831203281,
    "market_cap_change_percentage_24h": 5.83995,
    "circulating_supply": 19664781.0,
    "total_supply": 21000000.0,
    "max_supply": 21000000.0,
    "ath": 73738,
    "ath_change_percentage": -3.82897,
    "ath_date": "2024-03-14T07:10:36.635Z",
    "atl": 67.81,
    "atl_change_percentage": 104479.82623,
    "atl_date": "2013-07-06T00:00:00.000Z",
    "roi": null,
    "last_updated": "2024-03-26T11:15:43.525Z"
  },
  {
    "id": "ethereum",
    "symbol": "eth",
    "name": "Ethereum",
    "image": "https://assets.coingecko.com/coins/images/279/large/ethereum.png?1696501628",
    "current_price": 3639.39,
    "market_cap": 437322550708,
    "market_cap_rank": 2,
    "fully_diluted_valuation": 437322550708,
    "total_volume": 23199484638,
    "high_24h": 3682.96,
    "low_24h": 3435.6,
    "price_change_24h": 192.04,
    "price_change_percentage_24h": 5.57063,
    "market_cap_change_24h": 23223290563,
    "market_cap_change_percentage_24h": 5.60815,
    "circulating_supply": 120074016.275501,
    "total_supply": 120074016.275501,
    "max_supply": null,
    "ath": 4878.26,
    "ath_change_percentage": -25.23481,
    "ath_date": "2021-11-10T14:24:19.604Z",
    "atl": 0.432979,
    "atl_change_percentage": 842260.03188,
    "atl_date": "2015-10-20T00:00:00.000Z",
    "roi": {
      "times": 67.75506819792366,
      "currency": "btc",
      "percentage": 6775.506819792366
    },
    "last_updated": "2024-03-26T11:16:08.688Z"
  },
  {
    "id": "tether",
    "symbol": "usdt",
    "name": "Tether",
    "image": "https://assets.coingecko.com/coins/images/325/large/Tether.png?1696501661",
    "current_price": 0.998842,
    "market_cap": 104112976357,
    "market_cap_rank": 3,
    "fully_diluted_valuation": 104112976357,
    "total_volume": 77139216851,
    "high_24h": 1.006,
    "low_24h": 0.994709,
    "price_change_24h": -0.000813357069264553,
    "price_change_percentage_24h": -0.08136,
    "market_cap_change_24h": 147964218,
    "market_cap_change_percentage_24h": 0.14232,
    "circulating_supply": 104233700559.266,
    "total_supply": 104233700559.266,
    "max_supply": null,
    "ath": 1.32,
    "ath_change_percentage": -24.42672,
    "ath_date": "2018-07-24T00:00:00.000Z",
    "atl": 0.572521,
    "atl_change_percentage": 74.64977,
    "atl_date": "2015-03-02T00:00:00.000Z",
    "roi": null,
    "last_updated": "2024-03-26T11:11:29.913Z"
  },
  {
    "id": "binancecoin",
    "symbol": "bnb",
    "name": "BNB",
    "image": "https://assets.coingecko.com/coins/images/825/large/bnb-icon2_2x.png?1696501970",
    "current_price": 593.03,
    "market_cap": 91306160264,
    "market_cap_rank": 4,
    "fully_diluted_valuation": 91306160264,
    "total_volume": 2048320896,
    "high_24h": 599.37,
    "low_24h": 575.87,
    "price_change_24h": 9.37,
    "price_change_percentage_24h": 1.60542,
    "market_cap_change_24h": 1446238912,
    "market_cap_change_percentage_24h": 1.60944,
    "circulating_supply": 153856150.0,
    "total_supply": 153856150.0,
    "max_supply": 200000000.0,
    "ath": 686.31,
    "ath_change_percentage": -13.39942,
    "ath_date": "2021-05-10T07:24:17.097Z",
    "atl": 0.0398177,
    "atl_change_percentage": 1492566.74933,
    "atl_date": "2017-10-19T00:00:00.000Z",
    "roi": null,
    "last_updated": "2024-03-26T11:15:21.053Z"
  },
  {
    "id": "solana",
    "symbol": "sol",
    "name": "Solana",
    "image": "https://assets.coingecko.com/coins/images/4128/large/solana.png?1696504756",
    "current_price": 194.99,
    "market_cap": 86681603848,
    "market_cap_rank": 5,
    "fully_diluted_valuation": 111739202370,
    "total_volume": 4242624084,
    "high_24h": 196.29,
    "low_24h": 186.85,
    "price_change_24h": 5.3,
    "price_change_percentage_24h": 2.79488,
    "market_cap_change_24h": 2508075334,
    "market_cap_change_percentage_24h": 2.97965,
    "circulating_supply": 444184110.312142,
    "total_supply": 572587215.610271,
    "max_supply": null,
    "ath": 259.96,
    "ath_change_percentage": -24.71957,
    "ath_date": "2021-11-06T21:54:35.825Z",
    "atl": 0.500801,
    "atl_change_percentage": 38977.0728,
    "atl_date": "2020-05-11T19:35:23.449Z",
    "roi": null,
    "last_updated": "2024-03-26T11:15:24.002Z"
  },
  {
    "id": "ripple",
    "symbol": "xrp",
    "name": "XRP",
    "image": "https://assets.coingecko.com/coins/images/44/large/xrp-symbol-white-128.png?1696501442",
    "current_price": 0.64667,
    "market_cap": 35513573611,
    "market_cap_rank": 6,
    "fully_diluted_valuation": 64698402252,
    "total_volume": 2134123356,
    "high_24h": 0.656486,
    "low_24h": 0.627329,
    "price_change_24h": 0.01666943,
    "price_change_percentage_24h": 2.64594,
    "market_cap_change_24h": 947111577,
    "market_cap_change_percentage_24h": 2.73997,
    "circulating_supply": 54884241878.0,
    "total_supply": 99987762348.0,
    "max_supply": 100000000000.0,
    "ath": 3.4,
    "ath_change_percentage": -80.92667,
    "ath_date": "2018-01-07T00:00:00.000Z",
    "atl": 0.00268621,
    "atl_change_percentage": 24030.58877,
    "atl_date": "2014-05-22T00:00:00.000Z",
    "roi": null,
    "last_updated": "2024-03-26T11:15:01.641Z"
  },
  {
    "id": "staked-ether",
    "symbol": "steth",
    "name": "Lido Staked Ether",
    "image": "https://assets.coingecko.com/coins/images/13442/large/steth_logo.png?1696513206",
    "current_price": 3633.61,
    "market_cap": 35274510660,
    "market_cap_rank": 7,
    "fully_diluted_valuation": 35274510660,
    "total_volume": 118234569,
    "high_24h": 3669.11,
    "low_24h": 3429.44,
    "price_change_24h": 192.85,
    "price_change_percentage_24h": 5.60491,
    "market_cap_change_24h": 1680765600,
    "market_cap_change_percentage_24h": 5.00321,
    "circulating_supply": 9704189.01144664,
    "total_supply": 9704189.01144664,
    "max_supply": null,
    "ath": 4829.57,
    "ath_change_percentage": -24.58894,
    "ath_date": "2021-11-10T14:40:47.256Z",
    "atl": 482.9,
    "atl_change_percentage": 654.20566,
    "atl_date": "2020-12-22T04:08:21.854Z",
    "roi": null,
    "last_updated": "2024-03-26T11:15:18.388Z"
  },
  {
    "id": "usd-coin",
    "symbol": "usdc",
    "name": "USDC",
    "image": "https://assets.coingecko.com/coins/images/6319/large/usdc.png?1696506694",
    "current_price": 0.998823,
    "market_cap": 32241481508,
    "market_cap_rank": 8,
    "fully_diluted_valuation": 32251846145,
    "total_volume": 7781734120,
    "high_24h": 1.008,
    "low_24h": 0.99229,
    "price_change_24h": 0.00049421,
    "price_change_percentage_24h": 0.0495,
    "market_cap_change_24h": 148320873,
    "market_cap_change_percentage_24h": 0.46216,
    "circulating_supply": 32290417432.1313,
    "total_supply": 32300797800.532,
    "max_supply": null,
    "ath": 1.17,
    "ath_change_percentage": -14.82409,
    "ath_date": "2019-05-08T00:40:28.300Z",
    "atl": 0.877647,
    "atl_change_percentage": 13.81154,
    "atl_date": "2023-03-11T08:02:13.981Z",
    "roi": null,
    "last_updated": "2024-03-26T11:15:20.330Z"
  },
  {
    "id": "dogecoin",
    "symbol": "doge",
    "name": "Dogecoin",
    "image": "https://assets.coingecko.com/coins/images/5/large/dogecoin.png?1696501409",
    "current_price": 0.185257,
    "market_cap": 26582380300,
    "market_cap_rank": 9,
    "fully_diluted_valuation": 26583894359,
    "total_volume": 3210351667,
    "high_24h": 0.185395,
    "low_24h": 0.170668,
    "price_change_24h": 0.01393727,
    "price_change_percentage_24h": 8.13523,
    "market_cap_change_24h": 1977664675,
    "market_cap_change_percentage_24h": 8.03775,
    "circulating_supply": 143616516383.705,
    "total_supply": 143624696383.705,
    "max_supply": null,
    "ath": 0.731578,
    "ath_change_percentage": -74.7386,
    "ath_date": "2021-05-08T05:08:23.458Z",
    "atl": 8.69e-05,
    "atl_change_percentage": 212556.90588,
    "atl_date": "2015-05-06T00:00:00.000Z",
    "roi": null,
    "last_updated": "2024-03-26T11:16:23.152Z"
  },
  {
    "id": "cardano",
    "symbol": "ada",
    "name": "Cardano",
    "image": "https://assets.coingecko.com/coins/images/975/large/cardano.png?1696502090",
    "current_price": 0.679813,
    "market_cap": 24001813280,
    "market_cap_rank": 10,
    "fully_diluted_valuation": 30635598919,
    "total_volume": 624534807,
    "high_24h": 0.681909,
    "low_24h": 0.64014,
    "price_change_24h": 0.03288911,
    "price_change_percentage_24h": 5.08393,
    "market_cap_change_24h": 1179580642,
    "market_cap_change_percentage_24h": 5.16856,
    "circulating_supply": 35255768964.8805,
    "total_supply": 45000000000.0,
    "max_supply": 45000000000.0,
    "ath": 3.09,
    "ath_change_percentage": -77.90965,
    "ath_date": "2021-09-02T06:00:10.474Z",
    "atl": 0.01925275,
    "atl_change_percentage": 3441.88066,
    "atl_date": "2020-03-13T02:22:55.044Z",
    "roi": null,
    "last_updated": "2024-03-26T11:15:28.074Z"
  },
  {
    "id": "avalanche-2",
    "symbol": "avax",
    "name": "Avalanche",
    "image": "https://assets.coingecko.com/coins/images/12559/large/Avalanche_Circle_RedWhite_Trans.png?1696512369",
    "current_price": 58.18,
    "market_cap": 21998656788,
    "market_cap_rank": 11,
    "fully_diluted_valuation": 25419524663,
    "total_volume": 1035881669,
    "high_24h": 59.09,
    "low_24h": 56.9,
    "price_change_24h": 0.589853,
    "price_change_percentage_24h": 1.02428,
    "market_cap_change_24h": 175004191,
    "market_cap_change_percentage_24h": 0.8019,
    "circulating_supply": 377416610.663679,
    "total_supply": 436106210.281494,
    "max_supply": 720000000.0,
    "ath": 144.96,
    "ath_change_percentage": -59.7467,
    "ath_date": "2021-11-21T14:18:56.538Z",
    "atl": 2.8,
    "atl_change_percentage": 1983.1964,
    "atl_date": "2020-12-31T13:15:21.540Z",
    "roi": null,
    "last_updated": "2024-03-26T11:15:56.007Z"
  },
  {
    "id": "the-open-network",
    "symbol": "ton",
    "name": "Toncoin",
    "image": "https://assets.coingecko.com/coins/images/17980/large/ton_symbol.png?1696517498",
    "current_price": 5.25,
    "market_cap": 18234043668,
    "market_cap_rank": 12,
    "fully_diluted_valuation": 26821940145,
    "total_volume": 328876792,
    "high_24h": 5.69,
    "low_24h": 5.24,
    "price_change_24h": -0.12720905445900232,
    "price_change_percentage_24h": -2.36603,
    "market_cap_change_24h": -404551124.7106819,
    "market_cap_change_percentage_24h": -2.1705,
    "circulating_supply": 3470242616.48104,
    "total_supply": 5104662544.63833,
    "max_supply": null,
    "ath": 5.69,
    "ath_change_percentage": -7.71027,
    "ath_date": "2024-03-25T14:26:09.974Z",
    "atl": 0.519364,
    "atl_change_percentage": 910.24239,
    "atl_date": "2021-09-21T00:33:11.092Z",
    "roi": null,
    "last_updated": "2024-03-26T11:15:39.970Z"
  },
  {
    "id": "shiba-inu",
    "symbol": "shib",
    "name": "Shiba Inu",
    "image": "https://assets.coingecko.com/coins/images/11939/large/shiba.png?1696511800",
    "current_price": 3.036e-05,
    "market_cap": 17850370198,
    "market_cap_rank": 13,
    "fully_diluted_valuation": 30292060115,
    "total_volume": 1764701841,
    "high_24h": 3.027e-05,
    "low_24h": 2.75e-05,
    "price_change_24h": 2.69e-06,
    "price_change_percentage_24h": 9.7069,
    "market_cap_change_24h": 1498501934,
    "market_cap_change_percentage_24h": 9.1641,
    "circulating_supply": 589265151004543.8,
    "total_supply": 999982363421298.0,
    "max_supply": null,
    "ath": 8.616e-05,
    "ath_change_percentage": -65.2774,
    "ath_date": "2021-10-28T03:54:55.568Z",
    "atl": 5.6366e-11,
    "atl_change_percentage": 53075098.41944,
    "atl_date": "2020-11-28T11:26:25.838Z",
    "roi": null,
    "last_updated": "2024-03-26T11:15:22.627Z"
  },
  {
    "id": "polkadot",
    "symbol": "dot",
    "name": "Polkadot",
    "image": "https://assets.coingecko.com/coins/images/12171/large/polkadot.png?1696512008",
    "current_price": 10.0,
    "market_cap": 13456993395,
    "market_cap_rank": 14,
    "fully_diluted_valuation": 14266810018,
    "total_volume": 340334398,
    "high_24h": 10.06,
    "low_24h": 9.42,
    "price_change_24h": 0.518151,
    "price_change_percentage_24h": 5.46621,
    "market_cap_change_24h": 710889375,
    "market_cap_change_percentage_24h": 5.57731,
    "circulating_supply": 1345158453.90539,
    "total_supply": 1426107566.70922,
    "max_supply": null,
    "ath": 54.98,
    "ath_change_percentage": -81.76654,
    "ath_date": "2021-11-04T14:10:09.301Z",
    "atl": 2.7,
    "atl_change_percentage": 271.64366,
    "atl_date": "2020-08-20T05:48:11.359Z",
    "roi": null,
    "last_updated": "2024-03-26T11:14:59.448Z"
  },
  {
    "id": "chainlink",
    "symbol": "link",
    "name": "Chainlink",
    "image": "https://assets.coingecko.com/coins/images/877/large/chainlink-new-logo.png?1696502009",
    "current_price": 20.44,
    "market_cap": 11990051659,
    "market_cap_rank": 15,
    "fully_diluted_valuation": 20422504249,
    "total_volume": 549215306,
    "high_24h": 20.44,
    "low_24h": 18.83,
    "price_change_24h": 1.55,
    "price_change_percentage_24h": 8.21335,
    "market_cap_change_24h": 888754854,
    "market_cap_change_percentage_24h": 8.00587,
    "circulating_supply": 587099971.3083414,
    "total_supply": 1000000000.0,
    "max_supply": 1000000000.0,
    "ath": 52.7,
    "ath_change_percentage": -61.21089,
    "ath_date": "2021-05-10T00:13:57.214Z",
    "atl": 0.148183,
    "atl_change_percentage": 13694.10338,
    "atl_date": "2017-11-29T00:00:00.000Z",
    "roi": null,
    "last_updated": "2024-03-26T11:15:13.109Z"
  },
  {
    "id": "wrapped-bitcoin",
    "symbol": "wbtc",
    "name": "Wrapped Bitcoin",
    "image": "https://assets.coingecko.com/coins/images/7598/large/wrapped_bitcoin_wbtc.png?1696507857",
    "current_price": 70918,
    "market_cap": 11019159496,
    "market_cap_rank": 16,
    "fully_diluted_valuation": 11019159496,
    "total_volume": 432178310,
    "high_24h": 71136,
    "low_24h": 66769,
    "price_change_24h": 3997.14,
    "price_change_percentage_24h": 5.97296,
    "market_cap_change_24h": 618993198,
    "market_cap_change_percentage_24h": 5.95176,
    "circulating_supply": 155474.89789822,
    "total_supply": 155474.89789822,
    "max_supply": 155474.89789822,
    "ath": 73505,
    "ath_change_percentage": -3.46006,
    "ath_date": "2024-03-14T07:10:23.403Z",
    "atl": 3139.17,
    "atl_change_percentage": 2160.53668,
    "atl_date": "2019-04-02T00:00:00.000Z",
    "roi": null,
    "last_updated": "2024-03-26T11:15:51.772Z"
  },
  {
    "id": "tron",
    "symbol": "trx",
    "name": "TRON",
    "image": "https://assets.coingecko.com/coins/images/1094/large/tron-logo.png?1696502193",
    "current_price": 0.121895,
    "market_cap": 10691651147,
    "market_cap_rank": 17,
    "fully_diluted_valuation": 10691667282,
    "total_volume": 430462295,
    "high_24h": 0.12191,
    "low_24h": 0.118391,
    "price_change_24h": 0.00324842,
    "price_change_percentage_24h": 2.7379,
    "market_cap_change_24h": 268597208,
    "market_cap_change_percentage_24h": 2.57695,
    "circulating_supply": 87772573126.7822,
    "total_supply": 87772705585.7028,
    "max_supply": null,
    "ath": 0.231673,
    "ath_change_percentage": -47.44293,
    "ath_date": "2018-01-05T00:00:00.000Z",
    "atl": 0.00180434,
    "atl_change_percentage": 6648.19083,
    "atl_date": "2017-11-12T00:00:00.000Z",
    "roi": {
      "times": 63.15527651646905,
      "currency": "usd",
      "percentage": 6315.527651646905
    },
    "last_updated": "2024-03-26T11:15:16.038Z"
  },
  {
    "id": "matic-network",
    "symbol": "matic",
    "name": "Polygon",
    "image": "https://assets.coingecko.com/coins/images/4713/large/polygon.png?1698233745",
    "current_price": 1.065,
    "market_cap": 9888319413,
    "market_cap_rank": 18,
    "fully_diluted_valuation": 10652137808,
    "total_volume": 450111160,
    "high_24h": 1.079,
    "low_24h": 1.015,
    "price_change_24h": 0.03771633,
    "price_change_percentage_24h": 3.67158,
    "market_cap_change_24h": 338982727,
    "market_cap_change_percentage_24h": 3.5498,
    "circulating_supply": 9282943566.203985,
    "total_supply": 10000000000.0,
    "max_supply": 10000000000.0,
    "ath": 2.92,
    "ath_change_percentage": -63.3968,
    "ath_date": "2021-12-27T02:08:34.307Z",
    "atl": 0.00314376,
    "atl_change_percentage": 33854.42154,
    "atl_date": "2019-05-10T00:00:00.000Z",
    "roi": {
      "times": 403.9304170686684,
      "currency": "usd",
      "percentage": 40393.04170686685
    },
    "last_updated": "2024-03-26T11:15:05.684Z"
  },
  {
    "id": "uniswap",
    "symbol": "uni",
    "name": "Uniswap",
    "image": "https://assets.coingecko.com/coins/images/12504/large/uni.jpg?1696512319",
    "current_price": 12.78,
    "market_cap": 9635086469,
    "market_cap_rank": 19,
    "fully_diluted_valuation": 12782584971,
    "total_volume": 205030244,
    "high_24h": 12.89,
    "low_24h": 11.99,
    "price_change_24h": 0.670149,
    "price_change_percentage_24h": 5.53322,
    "market_cap_change_24h": 506419801,
    "market_cap_change_percentage_24h": 5.54758,
    "circulating_supply": 753766667.0,
    "total_supply": 1000000000.0,
    "max_supply": 1000000000.0,
    "ath": 44.92,
    "ath_change_percentage": -71.53099,
    "ath_date": "2021-05-03T05:25:04.822Z",
    "atl": 1.03,
    "atl_change_percentage": 1141.32106,
    "atl_date": "2020-09-17T01:20:38.214Z",
    "roi": null,
    "last_updated": "2024-03-26T11:15:04.089Z"
  },
  {
    "id": "bitcoin-cash",
    "symbol": "bch",
    "name": "Bitcoin Cash",
    "image": "https://assets.coingecko.com/coins/images/780/large/bitcoin-cash-circle.png?1696501932",
    "current_price": 488.84,
    "market_cap": 9631694061,
    "market_cap_rank": 20,
    "fully_diluted_valuation": 10278071636,
    "total_volume": 701157053,
    "high_24h": 504.17,
    "low_24h": 474.48,
    "price_change_24h": 10.02,
    "price_change_percentage_24h": 2.0924,
    "market_cap_change_24h": 210907812,
    "market_cap_change_percentage_24h": 2.23875,
    "circulating_supply": 19679331.1466508,
    "total_supply": 21000000.0,
    "max_supply": 21000000.0,
    "ath": 3785.82,
    "ath_change_percentage": -87.06015,
    "ath_date": "2017-12-20T00:00:00.000Z",
    "atl": 76.93,
    "atl_change_percentage": 536.74632,
    "atl_date": "2018-12-16T00:00:00.000Z",
    "roi": null,
    "last_updated": "2024-03-26T11:14:58.208Z"
  },
  {
    "id": "internet-computer",
    "symbol": "icp",
    "name": "Internet Computer",
    "image": "https://assets.coingecko.com/coins/images/14495/large/Internet_Computer_logo.png?1696514180",
    "current_price": 19.34,
    "market_cap": 8892053327,
    "market_cap_rank": 21,
    "fully_diluted_valuation": 9952699376,
    "total_volume": 660061586,
    "high_24h": 19.64,
    "low_24h": 16.65,
    "price_change_24h": 2.26,
    "price_change_percentage_24h": 13.25379,
    "market_cap_change_24h": 1012410355,
    "market_cap_change_percentage_24h": 12.84843,
    "circulating_supply": 461283143.805494,
    "total_supply": 516305097.245102,
    "max_supply": null,
    "ath": 700.65,
    "ath_change_percentage": -97.23814,
    "ath_date": "2021-05-10T16:05:53.653Z",
    "atl": 2.87,
    "atl_change_percentage": 575.4179,
    "atl_date": "2023-09-22T00:29:57.369Z",
    "roi": null,
    "last_updated": "2024-03-26T11:16:08.877Z"
  },
  {
    "id": "near",
    "symbol": "near",
    "name": "NEAR Protocol",
    "image": "https://assets.coingecko.com/coins/images/10365/large/near.jpg?1696510367",
    "current_price": 7.91,
    "market_cap": 8221928616,
    "market_cap_rank": 22,
    "fully_diluted_valuation": 9360483775,
    "total_volume": 699071602,
    "high_24h": 7.98,
    "low_24h": 7.3,
    "price_change_24h": 0.438099,
    "price_change_percentage_24h": 5.86315,
    "market_cap_change_24h": 441273418,
    "market_cap_change_percentage_24h": 5.67142,
    "circulating_supply": 1039156880.1147,
    "total_supply": 1183057111.05741,
    "max_supply": null,
    "ath": 20.44,
    "ath_change_percentage": -61.22058,
    "ath_date": "2022-01-16T22:09:45.873Z",
    "atl": 0.526762,
    "atl_change_percentage": 1404.62213,
    "atl_date": "2020-11-04T16:09:15.137Z",
    "roi": null,
    "last_updated": "2024-03-26T11:15:10.706Z"
  },
  {
    "id": "aptos",
    "symbol": "apt",
    "name": "Aptos",
    "image": "https://assets.coingecko.com/coins/images/26455/large/aptos_round.png?1696525528",
    "current_price": 18.2,
    "market_cap": 7189214073,
    "market_cap_rank": 23,
    "fully_diluted_valuation": 19724205462,
    "total_volume": 450428080,
    "high_24h": 18.24,
    "low_24h": 15.83,
    "price_change_24h": 2.04,
    "price_change_percentage_24h": 12.64576,
    "market_cap_change_24h": 787968555,
    "market_cap_change_percentage_24h": 12.30961,
    "circulating_supply": 396455238.813967,
    "total_supply": 1087707850.63218,
    "max_supply": null,
    "ath": 19.92,
    "ath_change_percentage": -8.88639,
    "ath_date": "2023-01-26T14:25:17.390Z",
    "atl": 3.08,
    "atl_change_percentage": 489.33112,
    "atl_date": "2022-12-29T21:35:14.796Z",
    "roi": null,
    "last_updated": "2024-03-26T11:15:07.157Z"
  },
  {
    "id": "litecoin",
    "symbol": "ltc",
    "name": "Litecoin",
    "image": "https://assets.coingecko.com/coins/images/2/large/litecoin.png?1696501400",
    "current_price": 91.43,
    "market_cap": 6800077275,
    "market_cap_rank": 24,
    "fully_diluted_valuation": 7682368540,
    "total_volume": 623563580,
    "high_24h": 92.44,
    "low_24h": 88.75,
    "price_change_24h": 2.02,
    "price_change_percentage_24h": 2.26082,
    "market_cap_change_24h": 153520183,
    "market_cap_change_percentage_24h": 2.30977,
    "circulating_supply": 74352914.4834713,
    "total_supply": 84000000.0,
    "max_supply": 84000000.0,
    "ath": 410.26,
    "ath_change_percentage": -77.66249,
    "ath_date": "2021-05-10T03:13:07.904Z",
    "atl": 1.15,
    "atl_change_percentage": 7876.88398,
    "atl_date": "2015-01-14T00:00:00.000Z",
    "roi": null,
    "last_updated": "2024-03-26T11:14:59.392Z"
  },
  {
    "id": "leo-token",
    "symbol": "leo",
    "name": "LEO Token",
    "image": "https://assets.coingecko.com/coins/images/8418/large/leo-token.png?1696508607",
    "current_price": 6.09,
    "market_cap": 5632731808,
    "market_cap_rank": 25,
    "fully_diluted_valuation": 5987637902,
    "total_volume": 2440201,
    "high_24h": 6.14,
    "low_24h": 6.03,
    "price_change_24h": 0.04270317,
    "price_change_percentage_24h": 0.70663,
    "market_cap_change_24h": 29083154,
    "market_cap_change_percentage_24h": 0.519,
    "circulating_supply": 926841265.9,
    "total_supply": 985239504.0,
    "max_supply": null,
    "ath": 8.14,
    "ath_change_percentage": -25.1822,
    "ath_date": "2022-02-08T17:40:10.285Z",
    "atl": 0.799859,
    "atl_change_percentage": 660.96965,
    "atl_date": "2019-12-24T15:14:35.376Z",
    "roi": null,
    "last_updated": "2024-03-26T11:15:36.608Z"
  },
  {
    "id": "blockstack",
    "symbol": "stx",
    "name": "Stacks",
    "image": "https://assets.coingecko.com/coins/images/2069/large/Stacks_Logo_png.png?1709979332",
    "current_price": 3.57,
    "market_cap": 5170739270,
    "market_cap_rank": 26,
    "fully_diluted_valuation": 6494974066,
    "total_volume": 177461037,
    "high_24h": 3.8,
    "low_24h": 3.44,
    "price_change_24h": 0.082292,
    "price_change_percentage_24h": 2.35851,
    "market_cap_change_24h": 117647269,
    "market_cap_change_percentage_24h": 2.32822,
    "circulating_supply": 1447335108.33208,
    "total_supply": 1818000000.0,
    "max_supply": 1818000000.0,
    "ath": 3.8,
    "ath_change_percentage": -5.96473,
    "ath_date": "2024-03-25T16:46:19.264Z",
    "atl": 0.04559639,
    "atl_change_percentage": 7742.82777,
    "atl_date": "2020-03-13T02:29:26.415Z",
    "roi": {
      "times": 28.7621257206647,
      "currency": "usd",
      "percentage": 2876.21257206647
    },
    "last_updated": "2024-03-26T11:15:24.247Z"
  },
  {
    "id": "filecoin",
    "symbol": "fil",
    "name": "Filecoin",
    "image": "https://assets.coingecko.com/coins/images/12817/large/filecoin.png?1696512609",
    "current_price": 9.57,
    "market_cap": 5064720692,
    "market_cap_rank": 27,
    "fully_diluted_valuation": 18822669997,
    "total_volume": 410626428,
    "high_24h": 9.72,
    "low_24h": 8.94,
    "price_change_24h": 0.535274,
    "price_change_percentage_24h": 5.9219,
    "market_cap_change_24h": 294891115,
    "market_cap_change_percentage_24h": 6.18242,
    "circulating_supply": 527605290.0,
    "total_supply": 1960807094.0,
    "max_supply": 1960807094.0,
    "ath": 236.84,
    "ath_change_percentage": -95.9344,
    "ath_date": "2021-04-01T13:29:41.564Z",
    "atl": 2.64,
    "atl_change_percentage": 264.60023,
    "atl_date": "2022-12-16T22:45:28.552Z",
    "roi": null,
    "last_updated": "2024-03-26T11:14:59.532Z"
  },
  {
    "id": "cosmos",
    "symbol": "atom",
    "name": "Cosmos Hub",
    "image": "https://assets.coingecko.com/coins/images/1481/large/cosmos_hub.png?1696502525",
    "current_price": 12.29,
    "market_cap": 4807400379,
    "market_cap_rank": 28,
    "fully_diluted_valuation": 4810374058,
    "total_volume": 254907803,
    "high_24h": 12.44,
    "low_24h": 11.7,
    "price_change_24h": 0.554984,
    "price_change_percentage_24h": 4.7291,
    "market_cap_change_24h": 195989557,
    "market_cap_change_percentage_24h": 4.2501,
    "circulating_supply": 390688369.813272,
    "total_supply": 390930035.085365,
    "max_supply": null,
    "ath": 44.45,
    "ath_change_percentage": -72.26601,
    "ath_date": "2022-01-17T00:34:41.497Z",
    "atl": 1.16,
    "atl_change_percentage": 962.63668,
    "atl_date": "2020-03-13T02:27:44.591Z",
    "roi": {
      "times": 121.9050082522434,
      "currency": "usd",
      "percentage": 12190.50082522434
    },
    "last_updated": "2024-03-26T11:16:11.048Z"
  },
  {
    "id": "ethereum-classic",
    "symbol": "etc",
    "name": "Ethereum Classic",
    "image": "https://assets.coingecko.com/coins/images/453/large/ethereum-classic-logo.png?1696501717",
    "current_price": 32.81,
    "market_cap": 4803870931,
    "market_cap_rank": 29,
    "fully_diluted_valuation": 6921954121,
    "total_volume": 237225937,
    "high_24h": 33.24,
    "low_24h": 31.03,
    "price_change_24h": 1.58,
    "price_change_percentage_24h": 5.05058,
    "market_cap_change_24h": 234628097,
    "market_cap_change_percentage_24h": 5.13494,
    "circulating_supply": 146226858.397316,
    "total_supply": 210700000.0,
    "max_supply": 210700000.0,
    "ath": 167.09,
    "ath_change_percentage": -80.32136,
    "ath_date": "2021-05-06T18:34:22.133Z",
    "atl": 0.615038,
    "atl_change_percentage": 5246.0309,
    "atl_date": "2016-07-25T00:00:00.000Z",
    "roi": {
      "times": 71.91949922940236,
      "currency": "usd",
      "percentage": 7191.949922940235
    },
    "last_updated": "2024-03-26T11:15:16.343Z"
  },
  {
    "id": "dai",
    "symbol": "dai",
    "name": "Dai",
    "image": "https://assets.coingecko.com/coins/images/9956/large/Badge_Dai.png?1696509996",
    "current_price": 0.998563,
    "market_cap": 4787256281,
    "market_cap_rank": 30,
    "fully_diluted_valuation": 4787256281,
    "total_volume": 364465810,
    "high_24h": 1.007,
    "low_24h": 0.994378,
    "price_change_24h": 2.568e-05,
    "price_change_percentage_24h": 0.00257,
    "market_cap_change_24h": -124044649.50892639,
    "market_cap_change_percentage_24h": -2.5257,
    "circulating_supply": 4788148988.91393,
    "total_supply": 4788148988.91393,
    "max_supply": null,
    "ath": 1.22,
    "ath_change_percentage": -18.03474,
    "ath_date": "2020-03-13T03:02:50.373Z",
    "atl": 0.88196,
    "atl_change_percentage": 13.28175,
    "atl_date": "2023-03-11T07:50:50.514Z",
    "roi": null,
    "last_updated": "2024-03-26T11:11:30.097Z"
  },
  {
    "id": "arbitrum",
    "symbol": "arb",
    "name": "Arbitrum",
    "image": "https://assets.coingecko.com/coins/images/16547/large/photo_2023-03-29_21.47.00.jpeg?1696516109",
    "current_price": 1.74,
    "market_cap": 4621498788,
    "market_cap_rank": 31,
    "fully_diluted_valuation": 17413731510,
    "total_volume": 519825833,
    "high_24h": 1.76,
    "low_24h": 1.68,
    "price_change_24h": 0.051125,
    "price_change_percentage_24h": 3.02994,
    "market_cap_change_24h": 131510764,
    "market_cap_change_percentage_24h": 2.92898,
    "circulating_supply": 2653939384.0,
    "total_supply": 10000000000.0,
    "max_supply": 10000000000.0,
    "ath": 2.39,
    "ath_change_percentage": -27.06149,
    "ath_date": "2024-01-12T12:29:59.231Z",
    "atl": 0.744925,
    "atl_change_percentage": 134.04192,
    "atl_date": "2023-09-11T19:40:49.196Z",
    "roi": null,
    "last_updated": "2024-03-26T11:16:24.857Z"
  },
  {
    "id": "immutable-x",
    "symbol": "imx",
    "name": "Immutable",
    "image": "https://assets.coingecko.com/coins/images/17233/large/immutableX-symbol-BLK-RGB.png?1696516787",
    "current_price": 3.17,
    "market_cap": 4514039917,
    "market_cap_rank": 32,
    "fully_diluted_valuation": 6344310075,
    "total_volume": 64544984,
    "high_24h": 3.2,
    "low_24h": 2.95,
    "price_change_24h": 0.185619,
    "price_change_percentage_24h": 6.21192,
    "market_cap_change_24h": 247470769,
    "market_cap_change_percentage_24h": 5.80023,
    "circulating_supply": 1423019954.3898141,
    "total_supply": 2000000000.0,
    "max_supply": 2000000000.0,
    "ath": 9.52,
    "ath_change_percentage": -66.62688,
    "ath_date": "2021-11-26T01:03:01.536Z",
    "atl": 0.378055,
    "atl_change_percentage": 740.3809,
    "atl_date": "2022-12-31T07:36:37.649Z",
    "roi": null,
    "last_updated": "2024-03-26T11:16:08.416Z"
  },
  {
    "id": "render-token",
    "symbol": "rndr",
    "name": "Render",
    "image": "https://assets.coingecko.com/coins/images/11636/large/rndr.png?1696511529",
    "current_price": 11.39,
    "market_cap": 4352726952,
    "market_cap_rank": 33,
    "fully_diluted_valuation": 6064870035,
    "total_volume": 316021239,
    "high_24h": 11.64,
    "low_24h": 10.91,
    "price_change_24h": 0.455837,
    "price_change_percentage_24h": 4.16742,
    "market_cap_change_24h": 178427804,
    "market_cap_change_percentage_24h": 4.27444,
    "circulating_supply": 381860659.292815,
    "total_supply": 532065368.572815,
    "max_supply": 532065368.572815,
    "ath": 13.53,
    "ath_change_percentage": -15.36358,
    "ath_date": "2024-03-17T16:30:24.636Z",
    "atl": 0.03665669,
    "atl_change_percentage": 31150.17307,
    "atl_date": "2020-06-16T13:22:25.900Z",
    "roi": null,
    "last_updated": "2024-03-26T11:15:11.085Z"
  },
  {
    "id": "hedera-hashgraph",
    "symbol": "hbar",
    "name": "Hedera",
    "image": "https://assets.coingecko.com/coins/images/3688/large/hbar.png?1696504364",
    "current_price": 0.123119,
    "market_cap": 4154156296,
    "market_cap_rank": 34,
    "fully_diluted_valuation": 6163272287,
    "total_volume": 83096066,
    "high_24h": 0.123491,
    "low_24h": 0.111008,
    "price_change_24h": 0.01098852,
    "price_change_percentage_24h": 9.79976,
    "market_cap_change_24h": 373193403,
    "market_cap_change_percentage_24h": 9.87033,
    "circulating_supply": 33700898670.7974,
    "total_supply": 50000000000.0,
    "max_supply": 50000000000.0,
    "ath": 0.569229,
    "ath_change_percentage": -78.30556,
    "ath_date": "2021-09-15T10:40:28.318Z",
    "atl": 0.00986111,
    "atl_change_percentage": 1152.30319,
    "atl_date": "2020-01-02T17:30:24.852Z",
    "roi": null,
    "last_updated": "2024-03-26T11:14:58.833Z"
  },
  {
    "id": "crypto-com-chain",
    "symbol": "cro",
    "name": "Cronos",
    "image": "https://assets.coingecko.com/coins/images/7310/large/cro_token_logo.png?1696507599",
    "current_price": 0.154133,
    "market_cap": 4103886607,
    "market_cap_rank": 35,
    "fully_diluted_valuation": 4626173866,
    "total_volume": 24680123,
    "high_24h": 0.154329,
    "low_24h": 0.141898,
    "price_change_24h": 0.01173474,
    "price_change_percentage_24h": 8.24076,
    "market_cap_change_24h": 299209292,
    "market_cap_change_percentage_24h": 7.86425,
    "circulating_supply": 26613050388.2866,
    "total_supply": 30000000000.0,
    "max_supply": null,
    "ath": 0.965407,
    "ath_change_percentage": -84.03941,
    "ath_date": "2021-11-24T15:53:54.855Z",
    "atl": 0.0121196,
    "atl_change_percentage": 1171.36798,
    "atl_date": "2019-02-08T00:00:00.000Z",
    "roi": null,
    "last_updated": "2024-03-26T11:16:25.356Z"
  },
  {
    "id": "optimism",
    "symbol": "op",
    "name": "Optimism",
    "image": "https://assets.coingecko.com/coins/images/25244/large/Optimism.png?1696524385",
    "current_price": 3.98,
    "market_cap": 4008702508,
    "market_cap_rank": 36,
    "fully_diluted_valuation": 17112150190,
    "total_volume": 342277416,
    "high_24h": 4.01,
    "low_24h": 3.76,
    "price_change_24h": 0.196172,
    "price_change_percentage_24h": 5.18735,
    "market_cap_change_24h": 204492118,
    "market_cap_change_percentage_24h": 5.37542,
    "circulating_supply": 1006141600.0,
    "total_supply": 4294967296.0,
    "max_supply": 4294967296.0,
    "ath": 4.84,
    "ath_change_percentage": -17.42789,
    "ath_date": "2024-03-06T08:35:50.817Z",
    "atl": 0.402159,
    "atl_change_percentage": 894.64335,
    "atl_date": "2022-06-18T20:54:52.178Z",
    "roi": null,
    "last_updated": "2024-03-26T11:15:32.376Z"
  },
  {
    "id": "stellar",
    "symbol": "xlm",
    "name": "Stellar",
    "image": "https://assets.coingecko.com/coins/images/100/large/Stellar_symbol_black_RGB.png?1696501482",
    "current_price": 0.139454,
    "market_cap": 4008633684,
    "market_cap_rank": 37,
    "fully_diluted_valuation": 6976093477,
    "total_volume": 116375111,
    "high_24h": 0.140022,
    "low_24h": 0.134294,
    "price_change_24h": 0.00443313,
    "price_change_percentage_24h": 3.2833,
    "market_cap_change_24h": 130110823,
    "market_cap_change_percentage_24h": 3.35465,
    "circulating_supply": 28732247972.0061,
    "total_supply": 50001787007.7091,
    "max_supply": 50001787007.7091,
    "ath": 0.875563,
    "ath_change_percentage": -84.04084,
    "ath_date": "2018-01-03T00:00:00.000Z",
    "atl": 0.00047612,
    "atl_change_percentage": 29247.95087,
    "atl_date": "2015-03-05T00:00:00.000Z",
    "roi": null,
    "last_updated": "2024-03-26T11:14:58.241Z"
  },
  {
    "id": "bittensor",
    "symbol": "tao",
    "name": "Bittensor",
    "image": "https://assets.coingecko.com/coins/images/28452/large/ARUsPeNQ_400x400.jpeg?1696527447",
    "current_price": 616.8,
    "market_cap": 4002591719,
    "market_cap_rank": 38,
    "fully_diluted_valuation": 12963048098,
    "total_volume": 25535272,
    "high_24h": 639.85,
    "low_24h": 594.55,
    "price_change_24h": 17.34,
    "price_change_percentage_24h": 2.89295,
    "market_cap_change_24h": 123639832,
    "market_cap_change_percentage_24h": 3.18745,
    "circulating_supply": 6484156.0,
    "total_supply": 21000000.0,
    "max_supply": 21000000.0,
    "ath": 757.6,
    "ath_change_percentage": -18.43603,
    "ath_date": "2024-03-07T18:45:36.466Z",
    "atl": 30.83,
    "atl_change_percentage": 1904.3246,
    "atl_date": "2023-05-14T08:57:53.732Z",
    "roi": null,
    "last_updated": "2024-03-26T11:15:00.001Z"
  },
  {
    "id": "okb",
    "symbol": "okb",
    "name": "OKB",
    "image": "https://assets.coingecko.com/coins/images/4463/large/WeChat_Image_20220118095654.png?1696505053",
    "current_price": 66.39,
    "market_cap": 3984700070,
    "market_cap_rank": 39,
    "fully_diluted_valuation": 15670343419,
    "total_volume": 16074887,
    "high_24h": 66.96,
    "low_24h": 64.45,
    "price_change_24h": 1.94,
    "price_change_percentage_24h": 3.01287,
    "market_cap_change_24h": 120816410,
    "market_cap_change_percentage_24h": 3.12681,
    "circulating_supply": 60000000.0,
    "total_supply": 235957685.3,
    "max_supply": 300000000.0,
    "ath": 73.8,
    "ath_change_percentage": -9.94492,
    "ath_date": "2024-03-14T00:30:12.502Z",
    "atl": 0.580608,
    "atl_change_percentage": 11347.25164,
    "atl_date": "2019-01-14T00:00:00.000Z",
    "roi": null,
    "last_updated": "2024-03-26T11:15:23.255Z"
  },
  {
    "id": "the-graph",
    "symbol": "grt",
    "name": "The Graph",
    "image": "https://assets.coingecko.com/coins/images/13397/large/Graph_Token.png?1696513159",
    "current_price": 0.411851,
    "market_cap": 3898519059,
    "market_cap_rank": 40,
    "fully_diluted_valuation": 4447494561,
    "total_volume": 185550494,
    "high_24h": 0.41733,
    "low_24h": 0.384157,
    "price_change_24h": 0.02096647,
    "price_change_percentage_24h": 5.36386,
    "market_cap_change_24h": 202930865,
    "market_cap_change_percentage_24h": 5.49117,
    "circulating_supply": 9456389405.24119,
    "total_supply": 10788004319.0,
    "max_supply": 10788004319.0,
    "ath": 2.84,
    "ath_change_percentage": -85.44928,
    "ath_date": "2021-02-12T07:28:45.775Z",
    "atl": 0.052051,
    "atl_change_percentage": 694.33488,
    "atl_date": "2022-11-22T10:05:03.503Z",
    "roi": null,
    "last_updated": "2024-03-26T11:15:34.328Z"
  },
  {
    "id": "injective-protocol",
    "symbol": "inj",
    "name": "Injective",
    "image": "https://assets.coingecko.com/coins/images/12882/large/Secondary_Symbol.png?1696512670",
    "current_price": 40.19,
    "market_cap": 3555768551,
    "market_cap_rank": 41,
    "fully_diluted_valuation": 4022716544,
    "total_volume": 236954161,
    "high_24h": 41.09,
    "low_24h": 36.58,
    "price_change_24h": 2.95,
    "price_change_percentage_24h": 7.91458,
    "market_cap_change_24h": 253803183,
    "market_cap_change_percentage_24h": 7.68643,
    "circulating_supply": 88392222.33,
    "total_supply": 100000000.0,
    "max_supply": null,
    "ath": 52.62,
    "ath_change_percentage": -23.42387,
    "ath_date": "2024-03-14T15:06:22.124Z",
    "atl": 0.657401,
    "atl_change_percentage": 6029.42213,
    "atl_date": "2020-11-03T16:19:30.576Z",
    "roi": null,
    "last_updated": "2024-03-26T11:15:46.043Z"
  },
  {
    "id": "pepe",
    "symbol": "pepe",
    "name": "Pepe",
    "image": "https://assets.coingecko.com/coins/images/29850/large/pepe-token.jpeg?1696528776",
    "current_price": 8.34e-06,
    "market_cap": 3510404317,
    "market_cap_rank": 42,
    "fully_diluted_valuation": 3510404317,
    "total_volume": 1146893300,
    "high_24h": 8.46e-06,
    "low_24h": 7.45e-06,
    "price_change_24h": 8.42059e-07,
    "price_change_percentage_24h": 11.23029,
    "market_cap_change_24h": 338013270,
    "market_cap_change_percentage_24h": 10.65484,
    "circulating_supply": 420690000000000.0,
    "total_supply": 420690000000000.0,
    "max_supply": 420690000000000.0,
    "ath": 1.064e-05,
    "ath_change_percentage": -21.42671,
    "ath_date": "2024-03-14T07:01:12.472Z",
    "atl": 5.5142e-08,
    "atl_change_percentage": 15057.99704,
    "atl_date": "2023-04-18T02:14:41.591Z",
    "roi": null,
    "last_updated": "2024-03-26T11:15:57.924Z"
  },
  {
    "id": "kaspa",
    "symbol": "kas",
    "name": "Kaspa",
    "image": "https://assets.coingecko.com/coins/images/25751/large/kaspa-icon-exchanges.png?1696524837",
    "current_price": 0.149101,
    "market_cap": 3447015636,
    "market_cap_rank": 43,
    "fully_diluted_valuation": 3453974757,
    "total_volume": 61314337,
    "high_24h": 0.149488,
    "low_24h": 0.145138,
    "price_change_24h": 0.00193682,
    "price_change_percentage_24h": 1.3161,
    "market_cap_change_24h": 51343049,
    "market_cap_change_percentage_24h": 1.51201,
    "circulating_supply": 23088387840.5108,
    "total_supply": 23135000587.9247,
    "max_supply": 28704026601.0,
    "ath": 0.189044,
    "ath_change_percentage": -21.02514,
    "ath_date": "2024-02-20T06:54:58.731Z",
    "atl": 0.00017105,
    "atl_change_percentage": 87182.76885,
    "atl_date": "2022-05-26T14:42:59.316Z",
    "roi": null,
    "last_updated": "2024-03-26T11:15:33.054Z"
  },
  {
    "id": "vechain",
    "symbol": "vet",
    "name": "VeChain",
    "image": "https://assets.coingecko.com/coins/images/1167/large/VET_Token_Icon.png?1710013505",
    "current_price": 0.04586762,
    "market_cap": 3336105214,
    "market_cap_rank": 44,
    "fully_diluted_valuation": 3944950152,
    "total_volume": 98387670,
    "high_24h": 0.04593302,
    "low_24h": 0.04280335,
    "price_change_24h": 0.00264778,
    "price_change_percentage_24h": 6.12631,
    "market_cap_change_24h": 193355455,
    "market_cap_change_percentage_24h": 6.15243,
    "circulating_supply": 72714516834.0,
    "total_supply": 85985041177.0,
    "max_supply": 86712634466.0,
    "ath": 0.280991,
    "ath_change_percentage": -83.65702,
    "ath_date": "2021-04-19T01:08:21.675Z",
    "atl": 0.00191713,
    "atl_change_percentage": 2295.36348,
    "atl_date": "2020-03-13T02:29:59.652Z",
    "roi": {
      "times": 3.407969636758275,
      "currency": "eth",
      "percentage": 340.7969636758275
    },
    "last_updated": "2024-03-26T11:14:58.609Z"
  },
  {
    "id": "thorchain",
    "symbol": "rune",
    "name": "THORChain",
    "image": "https://assets.coingecko.com/coins/images/6595/large/Rune200x200.png?1696506946",
    "current_price": 9.66,
    "market_cap": 3246482512,
    "market_cap_rank": 45,
    "fully_diluted_valuation": 4030053128,
    "total_volume": 730961897,
    "high_24h": 9.8,
    "low_24h": 8.56,
    "price_change_24h": 0.971368,
    "price_change_percentage_24h": 11.18164,
    "market_cap_change_24h": 321852841,
    "market_cap_change_percentage_24h": 11.00491,
    "circulating_supply": 335973151.0,
    "total_supply": 417063589.0,
    "max_supply": 500000000.0,
    "ath": 20.87,
    "ath_change_percentage": -53.58322,
    "ath_date": "2021-05-19T00:30:09.436Z",
    "atl": 0.00851264,
    "atl_change_percentage": 113684.38507,
    "atl_date": "2019-09-28T00:00:00.000Z",
    "roi": {
      "times": 253.17194385090872,
      "currency": "usd",
      "percentage": 25317.194385090872
    },
    "last_updated": "2024-03-26T11:15:58.402Z"
  },
  {
    "id": "dogwifcoin",
    "symbol": "wif",
    "name": "dogwifhat",
    "image": "https://assets.coingecko.com/coins/images/33566/large/dogwifhat.jpg?1702499428",
    "current_price": 3.18,
    "market_cap": 3224141588,
    "market_cap_rank": 46,
    "fully_diluted_valuation": 3224141588,
    "total_volume": 493897543,
    "high_24h": 3.24,
    "low_24h": 2.64,
    "price_change_24h": 0.444091,
    "price_change_percentage_24h": 16.22602,
    "market_cap_change_24h": 483100131,
    "market_cap_change_percentage_24h": 17.62469,
    "circulating_supply": 998926392.0,
    "total_supply": 998926392.0,
    "max_supply": 998926392.0,
    "ath": 3.47,
    "ath_change_percentage": -6.77424,
    "ath_date": "2024-03-15T02:11:25.613Z",
    "atl": 0.00155464,
    "atl_change_percentage": 208190.26361,
    "atl_date": "2023-12-13T07:13:50.873Z",
    "roi": null,
    "last_updated": "2024-03-26T11:16:12.539Z"
  },
  {
    "id": "fantom",
    "symbol": "ftm",
    "name": "Fantom",
    "image": "https://assets.coingecko.com/coins/images/4001/large/Fantom_round.png?1696504642",
    "current_price": 1.13,
    "market_cap": 3200823018,
    "market_cap_rank": 47,
    "fully_diluted_valuation": 3624799120,
    "total_volume": 654075850,
    "high_24h": 1.22,
    "low_24h": 1.073,
    "price_change_24h": 0.053706,
    "price_change_percentage_24h": 4.97166,
    "market_cap_change_24h": 172098877,
    "market_cap_change_percentage_24h": 5.68222,
    "circulating_supply": 2803634835.52659,
    "total_supply": 3175000000.0,
    "max_supply": 3175000000.0,
    "ath": 3.46,
    "ath_change_percentage": -66.87799,
    "ath_date": "2021-10-28T05:19:39.845Z",
    "atl": 0.00190227,
    "atl_change_percentage": 60120.1122,
    "atl_date": "2020-03-13T02:25:38.280Z",
    "roi": {
      "times": 36.7985425396762,
      "currency": "usd",
      "percentage": 3679.85425396762
    },
    "last_updated": "2024-03-26T11:15:19.154Z"
  },
  {
    "id": "theta-token",
    "symbol": "theta",
    "name": "Theta Network",
    "image": "https://assets.coingecko.com/coins/images/2538/large/theta-token-logo.png?1696503349",
    "current_price": 3.18,
    "market_cap": 3177398485,
    "market_cap_rank": 48,
    "fully_diluted_valuation": 3177398485,
    "total_volume": 90013409,
    "high_24h": 3.21,
    "low_24h": 2.87,
    "price_change_24h": 0.249984,
    "price_change_percentage_24h": 8.54299,
    "market_cap_change_24h": 248432175,
    "market_cap_change_percentage_24h": 8.48191,
    "circulating_supply": 1000000000.0,
    "total_supply": 1000000000.0,
    "max_supply": 1000000000.0,
    "ath": 15.72,
    "ath_change_percentage": -79.76827,
    "ath_date": "2021-04-16T13:15:11.190Z",
    "atl": 0.04039979,
    "atl_change_percentage": 7772.24648,
    "atl_date": "2020-03-13T02:24:16.483Z",
    "roi": {
      "times": 20.17450424767276,
      "currency": "usd",
      "percentage": 2017.450424767276
    },
    "last_updated": "2024-03-26T11:15:02.534Z"
  },
  {
    "id": "maker",
    "symbol": "mkr",
    "name": "Maker",
    "image": "https://assets.coingecko.com/coins/images/1364/large/Mark_Maker.png?1696502423",
    "current_price": 3331.3,
    "market_cap": 3079969289,
    "market_cap_rank": 49,
    "fully_diluted_valuation": 3257047471,
    "total_volume": 126655867,
    "high_24h": 3368.52,
    "low_24h": 3182.19,
    "price_change_24h": 126.94,
    "price_change_percentage_24h": 3.96162,
    "market_cap_change_24h": 117443684,
    "market_cap_change_percentage_24h": 3.96431,
    "circulating_supply": 924479.485522387,
    "total_supply": 977631.036950888,
    "max_supply": 1005577.0,
    "ath": 6292.31,
    "ath_change_percentage": -47.06532,
    "ath_date": "2021-05-03T21:54:29.333Z",
    "atl": 168.36,
    "atl_change_percentage": 1878.41787,
    "atl_date": "2020-03-16T20:52:36.527Z",
    "roi": null,
    "last_updated": "2024-03-26T11:15:22.854Z"
  },
  {
    "id": "mantle",
    "symbol": "mnt",
    "name": "Mantle",
    "image": "https://assets.coingecko.com/coins/images/30980/large/token-logo.png?1696529819",
    "current_price": 0.924246,
    "market_cap": 2987836464,
    "market_cap_rank": 50,
    "fully_diluted_valuation": 5746384723,
    "total_volume": 270521806,
    "high_24h": 0.926012,
    "low_24h": 0.82684,
    "price_change_24h": 0.09427,
    "price_change_percentage_24h": 11.35821,
    "market_cap_change_24h": 291337665,
    "market_cap_change_percentage_24h": 10.80429,
    "circulating_supply": 3233737802.03314,
    "total_supply": 6219316794.99,
    "max_supply": 6219316794.99,
    "ath": 1.094,
    "ath_change_percentage": -15.23822,
    "ath_date": "2024-03-11T08:55:07.391Z",
    "atl": 0.307978,
    "atl_change_percentage": 201.10606,
    "atl_date": "2023-10-18T02:50:46.942Z",
    "roi": null,
    "last_updated": "2024-03-26T11:16:19.122Z"
  },
  {
    "id": "fetch-ai",
    "symbol": "fet",
    "name": "Fetch.ai",
    "image": "https://assets.coingecko.com/coins/images/5681/large/Fetch.jpg?1696506140",
    "current_price": 2.82,
    "market_cap": 2950648681,
    "market_cap_rank": 51,
    "fully_diluted_valuation": 3260385284,
    "total_volume": 544598503,
    "high_24h": 2.93,
    "low_24h": 2.55,
    "price_change_24h": 0.219439,
    "price_change_percentage_24h": 8.4312,
    "market_cap_change_24h": 239363853,
    "market_cap_change_percentage_24h": 8.82843,
    "circulating_supply": 1043462805.0,
    "total_supply": 1152997575.0,
    "max_supply": 1152997575.0,
    "ath": 3.11,
    "ath_change_percentage": -8.64688,
    "ath_date": "2024-03-10T00:24:58.632Z",
    "atl": 0.00816959,
    "atl_change_percentage": 34655.23169,
    "atl_date": "2020-03-13T02:24:18.347Z",
    "roi": {
      "times": 31.55061049339234,
      "currency": "usd",
      "percentage": 3155.061049339234
    },
    "last_updated": "2024-03-26T11:15:12.350Z"
  },
  {
    "id": "lido-dao",
    "symbol": "ldo",
    "name": "Lido DAO",
    "image": "https://assets.coingecko.com/coins/images/13573/large/Lido_DAO.png?1696513326",
    "current_price": 3.24,
    "market_cap": 2893108420,
    "market_cap_rank": 52,
    "fully_diluted_valuation": 3244451805,
    "total_volume": 111137301,
    "high_24h": 3.39,
    "low_24h": 3.17,
    "price_change_24h": 0.04172047,
    "price_change_percentage_24h": 1.30312,
    "market_cap_change_24h": 38011098,
    "market_cap_change_percentage_24h": 1.33134,
    "circulating_supply": 891709476.331099,
    "total_supply": 1000000000.0,
    "max_supply": 1000000000.0,
    "ath": 7.3,
    "ath_change_percentage": -55.52049,
    "ath_date": "2021-08-20T08:35:20.158Z",
    "atl": 0.40615,
    "atl_change_percentage": 699.77431,
    "atl_date": "2022-06-18T20:55:12.035Z",
    "roi": null,
    "last_updated": "2024-03-26T11:15:27.581Z"
  },
  {
    "id": "arweave",
    "symbol": "ar",
    "name": "Arweave",
    "image": "https://assets.coingecko.com/coins/images/4343/large/oRt6SiEN_400x400.jpg?1696504946",
    "current_price": 42.23,
    "market_cap": 2768296479,
    "market_cap_rank": 53,
    "fully_diluted_valuation": 2768296479,
    "total_volume": 180788805,
    "high_24h": 44.63,
    "low_24h": 39.13,
    "price_change_24h": 3.07,
    "price_change_percentage_24h": 7.84792,
    "market_cap_change_24h": 206252987,
    "market_cap_change_percentage_24h": 8.05033,
    "circulating_supply": 65454185.5381511,
    "total_supply": 65454185.5381511,
    "max_supply": 66000000.0,
    "ath": 89.24,
    "ath_change_percentage": -52.5654,
    "ath_date": "2021-11-05T04:14:42.689Z",
    "atl": 0.298788,
    "atl_change_percentage": 14066.68792,
    "atl_date": "2020-01-31T06:47:36.543Z",
    "roi": {
      "times": 56.069381412763825,
      "currency": "usd",
      "percentage": 5606.938141276382
    },
    "last_updated": "2024-03-26T11:15:42.795Z"
  },
  {
    "id": "first-digital-usd",
    "symbol": "fdusd",
    "name": "First Digital USD",
    "image": "https://assets.coingecko.com/coins/images/31079/large/firstfigital.jpeg?1696529912",
    "current_price": 0.997675,
    "market_cap": 2616949745,
    "market_cap_rank": 54,
    "fully_diluted_valuation": 2616949846,
    "total_volume": 7795388944,
    "high_24h": 1.022,
    "low_24h": 0.991107,
    "price_change_24h": -0.00060431603501887,
    "price_change_percentage_24h": -0.06054,
    "market_cap_change_24h": -816202.7635436058,
    "market_cap_change_percentage_24h": -0.03118,
    "circulating_supply": 2621415328.85,
    "total_supply": 2621415429.85,
    "max_supply": null,
    "ath": 1.041,
    "ath_change_percentage": -4.03228,
    "ath_date": "2023-10-23T22:55:15.103Z",
    "atl": 0.942129,
    "atl_change_percentage": 6.07409,
    "atl_date": "2023-08-17T21:55:41.478Z",
    "roi": null,
    "last_updated": "2024-03-26T11:16:20.283Z"
  },
  {
    "id": "gala",
    "symbol": "gala",
    "name": "GALA",
    "image": "https://assets.coingecko.com/coins/images/12493/large/GALA_token_image_-_200PNG.png?1709725869",
    "current_price": 0.070225,
    "market_cap": 2612266248,
    "market_cap_rank": 55,
    "fully_diluted_valuation": 2613506305,
    "total_volume": 405679700,
    "high_24h": 0.072024,
    "low_24h": 0.066606,
    "price_change_24h": 0.00170505,
    "price_change_percentage_24h": 2.4884,
    "market_cap_change_24h": 66332227,
    "market_cap_change_percentage_24h": 2.60542,
    "circulating_supply": 37149767774.874,
    "total_supply": 37167402975.1101,
    "max_supply": 50000000000.0,
    "ath": 0.824837,
    "ath_change_percentage": -91.4652,
    "ath_date": "2021-11-26T01:03:48.731Z",
    "atl": 0.00013475,
    "atl_change_percentage": 52143.80385,
    "atl_date": "2020-12-28T08:46:48.367Z",
    "roi": null,
    "last_updated": "2024-03-26T11:15:48.560Z"
  },
  {
    "id": "monero",
    "symbol": "xmr",
    "name": "Monero",
    "image": "https://assets.coingecko.com/coins/images/69/large/monero_logo.png?1696501460",
    "current_price": 140.56,
    "market_cap": 2550562942,
    "market_cap_rank": 56,
    "fully_diluted_valuation": null,
    "total_volume": 53318510,
    "high_24h": 143.65,
    "low_24h": 138.17,
    "price_change_24h": -0.03554888579458293,
    "price_change_percentage_24h": -0.02528,
    "market_cap_change_24h": -4765421.1867723465,
    "market_cap_change_percentage_24h": -0.18649,
    "circulating_supply": 18147820.3764146,
    "total_supply": null,
    "max_supply": null,
    "ath": 542.33,
    "ath_change_percentage": -74.01522,
    "ath_date": "2018-01-09T00:00:00.000Z",
    "atl": 0.216177,
    "atl_change_percentage": 65088.39526,
    "atl_date": "2015-01-14T00:00:00.000Z",
    "roi": null,
    "last_updated": "2024-03-26T11:15:37.216Z"
  },
  {
    "id": "celestia",
    "symbol": "tia",
    "name": "Celestia",
    "image": "https://assets.coingecko.com/coins/images/31967/large/tia.jpg?1696530772",
    "current_price": 14.38,
    "market_cap": 2494380780,
    "market_cap_rank": 57,
    "fully_diluted_valuation": 14876031474,
    "total_volume": 112155805,
    "high_24h": 14.74,
    "low_24h": 13.64,
    "price_change_24h": 0.612425,
    "price_change_percentage_24h": 4.44902,
    "market_cap_change_24h": 110667675,
    "market_cap_change_percentage_24h": 4.64266,
    "circulating_supply": 173043527.749886,
    "total_supply": 1031999999.99989,
    "max_supply": null,
    "ath": 20.85,
    "ath_change_percentage": -30.7996,
    "ath_date": "2024-02-10T14:30:02.495Z",
    "atl": 2.08,
    "atl_change_percentage": 592.53124,
    "atl_date": "2023-10-31T15:14:31.951Z",
    "roi": null,
    "last_updated": "2024-03-26T11:16:21.778Z"
  },
  {
    "id": "floki",
    "symbol": "floki",
    "name": "FLOKI",
    "image": "https://assets.coingecko.com/coins/images/16746/large/PNG_image.png?1696516318",
    "current_price": 0.00024927,
    "market_cap": 2428492206,
    "market_cap_rank": 58,
    "fully_diluted_valuation": 2500325807,
    "total_volume": 669614292,
    "high_24h": 0.00025798,
    "low_24h": 0.00022872,
    "price_change_24h": 1.854e-05,
    "price_change_percentage_24h": 8.03542,
    "market_cap_change_24h": 182955996,
    "market_cap_change_percentage_24h": 8.14754,
    "circulating_supply": 9712703036055.0,
    "total_supply": 10000000000000.0,
    "max_supply": 10000000000000.0,
    "ath": 0.00033651,
    "ath_change_percentage": -25.8526,
    "ath_date": "2021-11-04T06:58:35.285Z",
    "atl": 8.428e-08,
    "atl_change_percentage": 295950.53334,
    "atl_date": "2021-07-06T01:11:20.438Z",
    "roi": null,
    "last_updated": "2024-03-26T11:15:20.384Z"
  },
  {
    "id": "sei-network",
    "symbol": "sei",
    "name": "Sei",
    "image": "https://assets.coingecko.com/coins/images/28205/large/Sei_Logo_-_Transparent.png?1696527207",
    "current_price": 0.862215,
    "market_cap": 2307360558,
    "market_cap_rank": 59,
    "fully_diluted_valuation": 8625646945,
    "total_volume": 119317735,
    "high_24h": 0.868314,
    "low_24h": 0.817949,
    "price_change_24h": 0.03492351,
    "price_change_percentage_24h": 4.22143,
    "market_cap_change_24h": 91553481,
    "market_cap_change_percentage_24h": 4.13183,
    "circulating_supply": 2675000000.0,
    "total_supply": 10000000000.0,
    "max_supply": null,
    "ath": 1.14,
    "ath_change_percentage": -24.06816,
    "ath_date": "2024-03-16T02:30:23.904Z",
    "atl": 0.095364,
    "atl_change_percentage": 807.48186,
    "atl_date": "2023-10-19T08:05:30.655Z",
    "roi": null,
    "last_updated": "2024-03-26T11:16:12.664Z"
  },
  {
    "id": "algorand",
    "symbol": "algo",
    "name": "Algorand",
    "image": "https://assets.coingecko.com/coins/images/4380/large/download.png?1696504978",
    "current_price": 0.283688,
    "market_cap": 2297273650,
    "market_cap_rank": 60,
    "fully_diluted_valuation": 2297273674,
    "total_volume": 107783455,
    "high_24h": 0.285186,
    "low_24h": 0.25625,
    "price_change_24h": 0.02474648,
    "price_change_percentage_24h": 9.55678,
    "market_cap_change_24h": 201198445,
    "market_cap_change_percentage_24h": 9.59882,
    "circulating_supply": 8073971708.97069,
    "total_supply": 8073971793.45978,
    "max_supply": 10000000000.0,
    "ath": 3.56,
    "ath_change_percentage": -91.99143,
    "ath_date": "2019-06-20T14:51:19.480Z",
    "atl": 0.087513,
    "atl_change_percentage": 225.88992,
    "atl_date": "2023-09-11T19:42:08.247Z",
    "roi": {
      "times": -0.8817966132692606,
      "currency": "usd",
      "percentage": -88.17966132692605
    },
    "last_updated": "2024-03-26T11:14:58.388Z"
  },
  {
    "id": "sui",
    "symbol": "sui",
    "name": "Sui",
    "image": "https://assets.coingecko.com/coins/images/26375/large/sui_asset.jpeg?1696525453",
    "current_price": 1.79,
    "market_cap": 2202280245,
    "market_cap_rank": 61,
    "fully_diluted_valuation": 17891383011,
    "total_volume": 297288127,
    "high_24h": 1.8,
    "low_24h": 1.66,
    "price_change_24h": 0.103637,
    "price_change_percentage_24h": 6.16086,
    "market_cap_change_24h": 128867956,
    "market_cap_change_percentage_24h": 6.21526,
    "circulating_supply": 1230916717.79423,
    "total_supply": 10000000000.0,
    "max_supply": 10000000000.0,
    "ath": 2.16,
    "ath_change_percentage": -17.00645,
    "ath_date": "2023-05-03T12:00:26.430Z",
    "atl": 0.364846,
    "atl_change_percentage": 391.91919,
    "atl_date": "2023-10-19T10:40:30.078Z",
    "roi": null,
    "last_updated": "2024-03-26T11:15:29.533Z"
  },
  {
    "id": "rocket-pool-eth",
    "symbol": "reth",
    "name": "Rocket Pool ETH",
    "image": "https://assets.coingecko.com/coins/images/20764/large/reth.png?1696520159",
    "current_price": 4013.49,
    "market_cap": 2176326244,
    "market_cap_rank": 62,
    "fully_diluted_valuation": 2176326244,
    "total_volume": 69558961,
    "high_24h": 4047.35,
    "low_24h": 3785.41,
    "price_change_24h": 210.36,
    "price_change_percentage_24h": 5.53137,
    "market_cap_change_24h": 113525193,
    "market_cap_change_percentage_24h": 5.50345,
    "circulating_supply": 541419.041204626,
    "total_supply": 541419.041204626,
    "max_supply": null,
    "ath": 4814.31,
    "ath_change_percentage": -16.40492,
    "ath_date": "2021-12-01T08:03:50.749Z",
    "atl": 887.26,
    "atl_change_percentage": 353.58863,
    "atl_date": "2022-06-18T20:55:45.957Z",
    "roi": null,
    "last_updated": "2024-03-26T11:15:28.597Z"
  },
  {
    "id": "flow",
    "symbol": "flow",
    "name": "Flow",
    "image": "https://assets.coingecko.com/coins/images/13446/large/5f6294c0c7a8cda55cb1c936_Flow_Wordmark.png?1696513210",
    "current_price": 1.44,
    "market_cap": 2159037361,
    "market_cap_rank": 63,
    "fully_diluted_valuation": 2159037361,
    "total_volume": 69518389,
    "high_24h": 1.45,
    "low_24h": 1.33,
    "price_change_24h": 0.101986,
    "price_change_percentage_24h": 7.62074,
    "market_cap_change_24h": 150888543,
    "market_cap_change_percentage_24h": 7.51381,
    "circulating_supply": 1496257868.0,
    "total_supply": 1496257868.42813,
    "max_supply": 1496257868.42813,
    "ath": 42.4,
    "ath_change_percentage": -96.59517,
    "ath_date": "2021-04-05T13:49:10.098Z",
    "atl": 0.391969,
    "atl_change_percentage": 268.28229,
    "atl_date": "2023-09-11T19:41:06.528Z",
    "roi": null,
    "last_updated": "2024-03-26T11:15:19.338Z"
  },
  {
    "id": "quant-network",
    "symbol": "qnt",
    "name": "Quant",
    "image": "https://assets.coingecko.com/coins/images/3370/large/5ZOu7brX_400x400.jpg?1696504070",
    "current_price": 145.82,
    "market_cap": 2124736607,
    "market_cap_rank": 64,
    "fully_diluted_valuation": 2134716910,
    "total_volume": 86145185,
    "high_24h": 148.69,
    "low_24h": 138.99,
    "price_change_24h": 5.29,
    "price_change_percentage_24h": 3.76383,
    "market_cap_change_24h": 68857675,
    "market_cap_change_percentage_24h": 3.34931,
    "circulating_supply": 14544176.164091088,
    "total_supply": 14612493.0,
    "max_supply": 14612493.0,
    "ath": 427.42,
    "ath_change_percentage": -65.77189,
    "ath_date": "2021-09-11T09:15:00.668Z",
    "atl": 0.215773,
    "atl_change_percentage": 67701.98322,
    "atl_date": "2018-08-23T00:00:00.000Z",
    "roi": {
      "times": 16.221398562426902,
      "currency": "eth",
      "percentage": 1622.1398562426903
    },
    "last_updated": "2024-03-26T11:15:57.421Z"
  },
  {
    "id": "mantle-staked-ether",
    "symbol": "meth",
    "name": "Mantle Staked Ether",
    "image": "https://assets.coingecko.com/coins/images/33345/large/symbol_transparent_bg.png?1701697066",
    "current_price": 3742.48,
    "market_cap": 1967117230,
    "market_cap_rank": 65,
    "fully_diluted_valuation": 1967117230,
    "total_volume": 3929930,
    "high_24h": 3767.83,
    "low_24h": 3491.48,
    "price_change_24h": 222.93,
    "price_change_percentage_24h": 6.33394,
    "market_cap_change_24h": 115584202,
    "market_cap_change_percentage_24h": 6.24262,
    "circulating_supply": 526084.604405326,
    "total_supply": 526084.604405326,
    "max_supply": null,
    "ath": 4221.1,
    "ath_change_percentage": -11.26813,
    "ath_date": "2024-03-12T00:54:55.007Z",
    "atl": 2142.02,
    "atl_change_percentage": 74.85661,
    "atl_date": "2023-12-18T10:41:32.686Z",
    "roi": null,
    "last_updated": "2024-03-26T11:15:42.465Z"
  },
  {
    "id": "conflux-token",
    "symbol": "cfx",
    "name": "Conflux",
    "image": "https://assets.coingecko.com/coins/images/13079/large/3vuYMbjN.png?1696512867",
    "current_price": 0.505128,
    "market_cap": 1942730022,
    "market_cap_rank": 66,
    "fully_diluted_valuation": 2768303788,
    "total_volume": 196663062,
    "high_24h": 0.524543,
    "low_24h": 0.500661,
    "price_change_24h": 0.00363198,
    "price_change_percentage_24h": 0.72423,
    "market_cap_change_24h": 15325048,
    "market_cap_change_percentage_24h": 0.79511,
    "circulating_supply": 3846198653.84045,
    "total_supply": 5480661843.64714,
    "max_supply": null,
    "ath": 1.7,
    "ath_change_percentage": -70.26909,
    "ath_date": "2021-03-27T03:43:35.178Z",
    "atl": 0.02199898,
    "atl_change_percentage": 2198.63834,
    "atl_date": "2022-12-30T08:16:30.345Z",
    "roi": null,
    "last_updated": "2024-03-26T11:15:32.857Z"
  },
  {
    "id": "beam-2",
    "symbol": "beam",
    "name": "Beam",
    "image": "https://assets.coingecko.com/coins/images/32417/large/chain-logo.png?1698114384",
    "current_price": 0.03654116,
    "market_cap": 1927402196,
    "market_cap_rank": 67,
    "fully_diluted_valuation": 2287288377,
    "total_volume": 33503498,
    "high_24h": 0.0375384,
    "low_24h": 0.03500027,
    "price_change_24h": 0.00125816,
    "price_change_percentage_24h": 3.5659,
    "market_cap_change_24h": 65974260,
    "market_cap_change_percentage_24h": 3.54428,
    "circulating_supply": 52643933931.79,
    "total_supply": 62473654150.0341,
    "max_supply": 62473654150.0341,
    "ath": 0.04416304,
    "ath_change_percentage": -17.01274,
    "ath_date": "2024-03-10T10:40:22.381Z",
    "atl": 0.0043383,
    "atl_change_percentage": 744.79366,
    "atl_date": "2023-10-29T08:20:14.064Z",
    "roi": null,
    "last_updated": "2024-03-26T11:15:22.360Z"
  },
  {
    "id": "aave",
    "symbol": "aave",
    "name": "Aave",
    "image": "https://assets.coingecko.com/coins/images/12645/large/AAVE.png?1696512452",
    "current_price": 130.25,
    "market_cap": 1924182230,
    "market_cap_rank": 68,
    "fully_diluted_valuation": 2084869659,
    "total_volume": 153628423,
    "high_24h": 131.75,
    "low_24h": 124.92,
    "price_change_24h": 3.58,
    "price_change_percentage_24h": 2.82438,
    "market_cap_change_24h": 53570698,
    "market_cap_change_percentage_24h": 2.86381,
    "circulating_supply": 14766829.923893845,
    "total_supply": 16000000.0,
    "max_supply": 16000000.0,
    "ath": 661.69,
    "ath_change_percentage": -80.30292,
    "ath_date": "2021-05-18T21:19:59.514Z",
    "atl": 26.02,
    "atl_change_percentage": 400.83731,
    "atl_date": "2020-11-05T09:20:11.928Z",
    "roi": null,
    "last_updated": "2024-03-26T11:16:14.236Z"
  },
  {
    "id": "jupiter-exchange-solana",
    "symbol": "jup",
    "name": "Jupiter",
    "image": "https://assets.coingecko.com/coins/images/34188/large/jup.png?1704266489",
    "current_price": 1.38,
    "market_cap": 1862001583,
    "market_cap_rank": 69,
    "fully_diluted_valuation": 13792604317,
    "total_volume": 232351105,
    "high_24h": 1.39,
    "low_24h": 1.29,
    "price_change_24h": 0.059004,
    "price_change_percentage_24h": 4.47386,
    "market_cap_change_24h": 75062667,
    "market_cap_change_percentage_24h": 4.20063,
    "circulating_supply": 1350000000.0,
    "total_supply": 10000000000.0,
    "max_supply": 10000000000.0,
    "ath": 2.0,
    "ath_change_percentage": -30.80386,
    "ath_date": "2024-01-31T15:02:47.304Z",
    "atl": 0.457464,
    "atl_change_percentage": 202.52259,
    "atl_date": "2024-02-21T18:31:05.083Z",
    "roi": null,
    "last_updated": "2024-03-26T11:16:03.430Z"
  },
  {
    "id": "bitcoin-cash-sv",
    "symbol": "bsv",
    "name": "Bitcoin SV",
    "image": "https://assets.coingecko.com/coins/images/6799/large/BSV.png?1696507128",
    "current_price": 90.27,
    "market_cap": 1775827917,
    "market_cap_rank": 70,
    "fully_diluted_valuation": 1895803503,
    "total_volume": 35513521,
    "high_24h": 90.82,
    "low_24h": 85.66,
    "price_change_24h": 4.1,
    "price_change_percentage_24h": 4.75487,
    "market_cap_change_24h": 80392830,
    "market_cap_change_percentage_24h": 4.74172,
    "circulating_supply": 19671018.75,
    "total_supply": 21000000.0,
    "max_supply": 21000000.0,
    "ath": 489.75,
    "ath_change_percentage": -81.5896,
    "ath_date": "2021-04-16T17:09:04.630Z",
    "atl": 21.43,
    "atl_change_percentage": 320.64727,
    "atl_date": "2023-06-10T04:32:12.266Z",
    "roi": null,
    "last_updated": "2024-03-26T11:15:48.596Z"
  },
  {
    "id": "bonk",
    "symbol": "bonk",
    "name": "Bonk",
    "image": "https://assets.coingecko.com/coins/images/28600/large/bonk.jpg?1696527587",
    "current_price": 2.642e-05,
    "market_cap": 1746222120,
    "market_cap_rank": 71,
    "fully_diluted_valuation": 2480933532,
    "total_volume": 250625794,
    "high_24h": 2.682e-05,
    "low_24h": 2.315e-05,
    "price_change_24h": 3.17e-06,
    "price_change_percentage_24h": 13.62452,
    "market_cap_change_24h": 214810701,
    "market_cap_change_percentage_24h": 14.02698,
    "circulating_supply": 65829046987150.32,
    "total_supply": 93526183276778.0,
    "max_supply": 93526183276778.0,
    "ath": 4.547e-05,
    "ath_change_percentage": -41.61136,
    "ath_date": "2024-03-04T17:05:29.594Z",
    "atl": 8.6142e-08,
    "atl_change_percentage": 30720.82847,
    "atl_date": "2022-12-29T22:48:46.755Z",
    "roi": null,
    "last_updated": "2024-03-26T11:15:08.699Z"
  },
  {
    "id": "elrond-erd-2",
    "symbol": "egld",
    "name": "MultiversX",
    "image": "https://assets.coingecko.com/coins/images/12335/large/egld-token-logo.png?1696512162",
    "current_price": 64.29,
    "market_cap": 1721579146,
    "market_cap_rank": 72,
    "fully_diluted_valuation": 1721910877,
    "total_volume": 39058338,
    "high_24h": 64.8,
    "low_24h": 61.91,
    "price_change_24h": 1.98,
    "price_change_percentage_24h": 3.17078,
    "market_cap_change_24h": 54248714,
    "market_cap_change_percentage_24h": 3.25363,
    "circulating_supply": 26737296.0,
    "total_supply": 26742448.0,
    "max_supply": 31415926.0,
    "ath": 545.64,
    "ath_change_percentage": -88.19594,
    "ath_date": "2021-11-23T10:33:26.737Z",
    "atl": 6.51,
    "atl_change_percentage": 889.87186,
    "atl_date": "2020-10-07T01:44:53.554Z",
    "roi": null,
    "last_updated": "2024-03-26T11:14:58.758Z"
  },
  {
    "id": "dydx-chain",
    "symbol": "dydx",
    "name": "dYdX",
    "image": "https://assets.coingecko.com/coins/images/32594/large/dydx.png?1698673495",
    "current_price": 3.68,
    "market_cap": 1713617468,
    "market_cap_rank": 73,
    "fully_diluted_valuation": 2623382602,
    "total_volume": 15155834,
    "high_24h": 3.69,
    "low_24h": 3.36,
    "price_change_24h": 0.291255,
    "price_change_percentage_24h": 8.59795,
    "market_cap_change_24h": 133338606,
    "market_cap_change_percentage_24h": 8.43766,
    "circulating_supply": 464677529.0,
    "total_supply": 711376353.0,
    "max_supply": 1000000000.0,
    "ath": 4.52,
    "ath_change_percentage": -18.29058,
    "ath_date": "2024-03-07T22:19:11.131Z",
    "atl": 2.3,
    "atl_change_percentage": 60.30833,
    "atl_date": "2024-01-03T12:14:30.340Z",
    "roi": null,
    "last_updated": "2024-03-26T11:14:41.407Z"
  },
  {
    "id": "starknet",
    "symbol": "strk",
    "name": "Starknet",
    "image": "https://assets.coingecko.com/coins/images/26433/large/starknet.png?1696525507",
    "current_price": 2.34,
    "market_cap": 1705784706,
    "market_cap_rank": 74,
    "fully_diluted_valuation": 23431108606,
    "total_volume": 211787793,
    "high_24h": 2.4,
    "low_24h": 2.14,
    "price_change_24h": 0.18313,
    "price_change_percentage_24h": 8.49211,
    "market_cap_change_24h": 133396010,
    "market_cap_change_percentage_24h": 8.48365,
    "circulating_supply": 728000000.0,
    "total_supply": 10000000000.0,
    "max_supply": 10000000000.0,
    "ath": 4.41,
    "ath_change_percentage": -46.76933,
    "ath_date": "2024-02-20T12:05:13.556Z",
    "atl": 1.7,
    "atl_change_percentage": 38.48072,
    "atl_date": "2024-02-21T14:29:50.266Z",
    "roi": null,
    "last_updated": "2024-03-26T11:16:03.356Z"
  },
  {
    "id": "havven",
    "symbol": "snx",
    "name": "Synthetix Network",
    "image": "https://assets.coingecko.com/coins/images/3406/large/SNX.png?1696504103",
    "current_price": 5.06,
    "market_cap": 1659340466,
    "market_cap_rank": 75,
    "fully_diluted_valuation": 1661486511,
    "total_volume": 116684557,
    "high_24h": 5.2,
    "low_24h": 4.67,
    "price_change_24h": 0.337294,
    "price_change_percentage_24h": 7.1483,
    "market_cap_change_24h": 113647334,
    "market_cap_change_percentage_24h": 7.35252,
    "circulating_supply": 327769196.13952357,
    "total_supply": 328193104.088774,
    "max_supply": 328193104.088774,
    "ath": 28.53,
    "ath_change_percentage": -82.20788,
    "ath_date": "2021-02-14T01:12:38.505Z",
    "atl": 0.0347864,
    "atl_change_percentage": 14493.33996,
    "atl_date": "2019-01-06T00:00:00.000Z",
    "roi": {
      "times": 9.111628931359187,
      "currency": "usd",
      "percentage": 911.1628931359186
    },
    "last_updated": "2024-03-26T11:15:22.318Z"
  },
  {
    "id": "axie-infinity",
    "symbol": "axs",
    "name": "Axie Infinity",
    "image": "https://assets.coingecko.com/coins/images/13029/large/axie_infinity_logo.png?1696512817",
    "current_price": 11.31,
    "market_cap": 1612543404,
    "market_cap_rank": 76,
    "fully_diluted_valuation": 3059989825,
    "total_volume": 82389881,
    "high_24h": 11.36,
    "low_24h": 10.49,
    "price_change_24h": 0.712723,
    "price_change_percentage_24h": 6.72317,
    "market_cap_change_24h": 103910106,
    "market_cap_change_percentage_24h": 6.8877,
    "circulating_supply": 142283714.676133,
    "total_supply": 270000000.0,
    "max_supply": 270000000.0,
    "ath": 164.9,
    "ath_change_percentage": -93.12499,
    "ath_date": "2021-11-06T19:29:29.482Z",
    "atl": 0.123718,
    "atl_change_percentage": 9063.36132,
    "atl_date": "2020-11-06T08:05:43.662Z",
    "roi": null,
    "last_updated": "2024-03-26T11:15:13.403Z"
  },
  {
    "id": "the-sandbox",
    "symbol": "sand",
    "name": "The Sandbox",
    "image": "https://assets.coingecko.com/coins/images/12129/large/sandbox_logo.jpg?1696511971",
    "current_price": 0.714097,
    "market_cap": 1609633359,
    "market_cap_rank": 77,
    "fully_diluted_valuation": 2144527073,
    "total_volume": 176525240,
    "high_24h": 0.716332,
    "low_24h": 0.667427,
    "price_change_24h": 0.03985891,
    "price_change_percentage_24h": 5.9117,
    "market_cap_change_24h": 91299407,
    "market_cap_change_percentage_24h": 6.01313,
    "circulating_supply": 2251731926.2233224,
    "total_supply": 3000000000.0,
    "max_supply": 3000000000.0,
    "ath": 8.4,
    "ath_change_percentage": -91.47733,
    "ath_date": "2021-11-25T06:04:40.957Z",
    "atl": 0.02897764,
    "atl_change_percentage": 2369.59713,
    "atl_date": "2020-11-04T15:59:14.441Z",
    "roi": null,
    "last_updated": "2024-03-26T11:15:47.998Z"
  },
  {
    "id": "wrapped-eeth",
    "symbol": "weeth",
    "name": "Wrapped eETH",
    "image": "https://assets.coingecko.com/coins/images/33033/large/weETH.png?1701438396",
    "current_price": 3769.1,
    "market_cap": 1589661381,
    "market_cap_rank": 78,
    "fully_diluted_valuation": 1589661381,
    "total_volume": 58653755,
    "high_24h": 3798.27,
    "low_24h": 3546.0,
    "price_change_24h": 211.0,
    "price_change_percentage_24h": 5.93024,
    "market_cap_change_24h": 186889043,
    "market_cap_change_percentage_24h": 13.32283,
    "circulating_supply": 421791.562197919,
    "total_supply": 421791.562197919,
    "max_supply": null,
    "ath": 4196.87,
    "ath_change_percentage": -10.0307,
    "ath_date": "2024-03-13T08:29:59.938Z",
    "atl": 2231.18,
    "atl_change_percentage": 69.2335,
    "atl_date": "2024-01-08T03:35:28.624Z",
    "roi": null,
    "last_updated": "2024-03-26T11:15:42.464Z"
  },
  {
    "id": "singularitynet",
    "symbol": "agix",
    "name": "SingularityNET",
    "image": "https://assets.coingecko.com/coins/images/2138/large/singularitynet.png?1696503103",
    "current_price": 1.21,
    "market_cap": 1551127817,
    "market_cap_rank": 79,
    "fully_diluted_valuation": 1688499946,
    "total_volume": 315925206,
    "high_24h": 1.24,
    "low_24h": 1.11,
    "price_change_24h": 0.082834,
    "price_change_percentage_24h": 7.35466,
    "market_cap_change_24h": 104944336,
    "market_cap_change_percentage_24h": 7.25664,
    "circulating_supply": 1279381312.64262,
    "total_supply": 1392686826.98352,
    "max_supply": 2000000000.0,
    "ath": 1.46,
    "ath_change_percentage": -16.71174,
    "ath_date": "2024-03-10T00:24:59.207Z",
    "atl": 0.00747159,
    "atl_change_percentage": 16184.45734,
    "atl_date": "2020-03-13T02:24:16.528Z",
    "roi": {
      "times": 11.09110056589875,
      "currency": "usd",
      "percentage": 1109.110056589875
    },
    "last_updated": "2024-03-26T11:16:09.733Z"
  },
  {
    "id": "bittorrent",
    "symbol": "btt",
    "name": "BitTorrent",
    "image": "https://assets.coingecko.com/coins/images/22457/large/btt_logo.png?1696521780",
    "current_price": 1.6e-06,
    "market_cap": 1540521436,
    "market_cap_rank": 80,
    "fully_diluted_valuation": 1575132297,
    "total_volume": 86441930,
    "high_24h": 1.61e-06,
    "low_24h": 1.51e-06,
    "price_change_24h": 7.7028e-08,
    "price_change_percentage_24h": 5.07189,
    "market_cap_change_24h": 69573128,
    "market_cap_change_percentage_24h": 4.72981,
    "circulating_supply": 968246428571000.0,
    "total_supply": 990000000000000.0,
    "max_supply": 990000000000000.0,
    "ath": 3.43e-06,
    "ath_change_percentage": -53.60332,
    "ath_date": "2022-01-21T04:00:31.909Z",
    "atl": 3.65368e-07,
    "atl_change_percentage": 335.73295,
    "atl_date": "2023-10-13T05:10:41.241Z",
    "roi": null,
    "last_updated": "2024-03-26T11:15:18.040Z"
  },
  {
    "id": "pyth-network",
    "symbol": "pyth",
    "name": "Pyth Network",
    "image": "https://assets.coingecko.com/coins/images/31924/large/pyth.png?1701245725",
    "current_price": 0.980739,
    "market_cap": 1474505211,
    "market_cap_rank": 81,
    "fully_diluted_valuation": 9830034741,
    "total_volume": 90721224,
    "high_24h": 0.993413,
    "low_24h": 0.931374,
    "price_change_24h": 0.02669491,
    "price_change_percentage_24h": 2.79808,
    "market_cap_change_24h": 40319990,
    "market_cap_change_percentage_24h": 2.81135,
    "circulating_supply": 1500000000.0,
    "total_supply": 10000000000.0,
    "max_supply": 10000000000.0,
    "ath": 1.2,
    "ath_change_percentage": -17.51211,
    "ath_date": "2024-03-16T07:01:15.357Z",
    "atl": 0.228806,
    "atl_change_percentage": 331.30761,
    "atl_date": "2024-01-08T03:29:54.594Z",
    "roi": null,
    "last_updated": "2024-03-26T11:16:24.903Z"
  },
  {
    "id": "worldcoin-wld",
    "symbol": "wld",
    "name": "Worldcoin",
    "image": "https://assets.coingecko.com/coins/images/31069/large/worldcoin.jpeg?1696529903",
    "current_price": 9.15,
    "market_cap": 1453978167,
    "market_cap_rank": 82,
    "fully_diluted_valuation": 91463534639,
    "total_volume": 413868466,
    "high_24h": 9.43,
    "low_24h": 8.37,
    "price_change_24h": 0.624384,
    "price_change_percentage_24h": 7.32782,
    "market_cap_change_24h": 115818969,
    "market_cap_change_percentage_24h": 8.6551,
    "circulating_supply": 158968071.047321,
    "total_supply": 10000000000.0,
    "max_supply": 10000000000.0,
    "ath": 11.74,
    "ath_change_percentage": -21.64194,
    "ath_date": "2024-03-10T00:10:42.330Z",
    "atl": 0.973104,
    "atl_change_percentage": 845.39942,
    "atl_date": "2023-09-13T07:36:44.064Z",
    "roi": null,
    "last_updated": "2024-03-26T11:15:21.916Z"
  },
  {
    "id": "ether-fi-staked-eth",
    "symbol": "eeth",
    "name": "ether.fi Staked ETH",
    "image": "https://assets.coingecko.com/coins/images/33049/large/ether.fi_eETH.png?1700473063",
    "current_price": 3640.47,
    "market_cap": 1444745268,
    "market_cap_rank": 83,
    "fully_diluted_valuation": 3029366930,
    "total_volume": 203438,
    "high_24h": 3667.48,
    "low_24h": 3416.41,
    "price_change_24h": 198.2,
    "price_change_percentage_24h": 5.75786,
    "market_cap_change_24h": 93323920,
    "market_cap_change_percentage_24h": 6.90561,
    "circulating_supply": 397599.4519441278,
    "total_supply": 833693.425397326,
    "max_supply": null,
    "ath": 15396.66,
    "ath_change_percentage": -76.36189,
    "ath_date": "2024-03-24T04:26:06.292Z",
    "atl": 2155.76,
    "atl_change_percentage": 68.82603,
    "atl_date": "2024-02-08T11:26:30.368Z",
    "roi": null,
    "last_updated": "2024-03-26T11:16:18.619Z"
  },
  {
    "id": "ordinals",
    "symbol": "ordi",
    "name": "ORDI",
    "image": "https://assets.coingecko.com/coins/images/30162/large/ordi.png?1696529082",
    "current_price": 68.45,
    "market_cap": 1437822276,
    "market_cap_rank": 84,
    "fully_diluted_valuation": 1437822276,
    "total_volume": 263994516,
    "high_24h": 69.21,
    "low_24h": 63.0,
    "price_change_24h": 4.84,
    "price_change_percentage_24h": 7.60632,
    "market_cap_change_24h": 101409144,
    "market_cap_change_percentage_24h": 7.58816,
    "circulating_supply": 21000000.0,
    "total_supply": 21000000.0,
    "max_supply": null,
    "ath": 95.52,
    "ath_change_percentage": -28.20537,
    "ath_date": "2024-03-05T01:45:22.816Z",
    "atl": 2.86,
    "atl_change_percentage": 2297.08098,
    "atl_date": "2023-09-11T15:22:32.140Z",
    "roi": null,
    "last_updated": "2024-03-26T11:16:14.811Z"
  },
  {
    "id": "mina-protocol",
    "symbol": "mina",
    "name": "Mina Protocol",
    "image": "https://assets.coingecko.com/coins/images/15628/large/JM4_vQ34_400x400.png?1696515261",
    "current_price": 1.3,
    "market_cap": 1401273935,
    "market_cap_rank": 85,
    "fully_diluted_valuation": 1486166418,
    "total_volume": 41725032,
    "high_24h": 1.32,
    "low_24h": 1.23,
    "price_change_24h": 0.066532,
    "price_change_percentage_24h": 5.38631,
    "market_cap_change_24h": 71641815,
    "market_cap_change_percentage_24h": 5.38809,
    "circulating_supply": 1074819320.84004,
    "total_supply": 1139934412.84004,
    "max_supply": null,
    "ath": 9.09,
    "ath_change_percentage": -85.6204,
    "ath_date": "2021-06-01T01:42:37.064Z",
    "atl": 0.351341,
    "atl_change_percentage": 272.04701,
    "atl_date": "2023-10-11T04:00:22.740Z",
    "roi": null,
    "last_updated": "2024-03-26T11:16:21.006Z"
  },
  {
    "id": "kucoin-shares",
    "symbol": "kcs",
    "name": "KuCoin",
    "image": "https://assets.coingecko.com/coins/images/1047/large/sa9z79.png?1696502152",
    "current_price": 14.4,
    "market_cap": 1387679629,
    "market_cap_rank": 86,
    "fully_diluted_valuation": 2072243543,
    "total_volume": 325062,
    "high_24h": 14.56,
    "low_24h": 14.18,
    "price_change_24h": 0.194258,
    "price_change_percentage_24h": 1.36769,
    "market_cap_change_24h": 19116324,
    "market_cap_change_percentage_24h": 1.39682,
    "circulating_supply": 96287258.2887907,
    "total_supply": 143787258.288707,
    "max_supply": null,
    "ath": 28.83,
    "ath_change_percentage": -49.95385,
    "ath_date": "2021-12-01T15:09:35.541Z",
    "atl": 0.342863,
    "atl_change_percentage": 4108.16654,
    "atl_date": "2019-02-07T00:00:00.000Z",
    "roi": null,
    "last_updated": "2024-03-26T11:15:14.445Z"
  },
  {
    "id": "flare-networks",
    "symbol": "flr",
    "name": "Flare",
    "image": "https://assets.coingecko.com/coins/images/28624/large/FLR-icon200x200.png?1696527609",
    "current_price": 0.03747497,
    "market_cap": 1381071932,
    "market_cap_rank": 87,
    "fully_diluted_valuation": 3820649737,
    "total_volume": 21761145,
    "high_24h": 0.03825425,
    "low_24h": 0.03588539,
    "price_change_24h": 0.00115366,
    "price_change_percentage_24h": 3.17625,
    "market_cap_change_24h": 46273941,
    "market_cap_change_percentage_24h": 3.46674,
    "circulating_supply": 36782300139.3725,
    "total_supply": 101755949181.416,
    "max_supply": null,
    "ath": 0.150073,
    "ath_change_percentage": -74.99431,
    "ath_date": "2023-01-10T03:14:05.921Z",
    "atl": 0.00827405,
    "atl_change_percentage": 353.54778,
    "atl_date": "2023-10-19T03:35:41.663Z",
    "roi": null,
    "last_updated": "2024-03-26T11:15:20.561Z"
  },
  {
    "id": "chiliz",
    "symbol": "chz",
    "name": "Chiliz",
    "image": "https://assets.coingecko.com/coins/images/8834/large/CHZ_Token_updated.png?1696508986",
    "current_price": 0.151031,
    "market_cap": 1345327931,
    "market_cap_rank": 88,
    "fully_diluted_valuation": 1345327931,
    "total_volume": 91572659,
    "high_24h": 0.152117,
    "low_24h": 0.140241,
    "price_change_24h": 0.00969751,
    "price_change_percentage_24h": 6.86145,
    "market_cap_change_24h": 87651281,
    "market_cap_change_percentage_24h": 6.9693,
    "circulating_supply": 8888888888.0,
    "total_supply": 8888888888.0,
    "max_supply": 8888888888.0,
    "ath": 0.878633,
    "ath_change_percentage": -82.76247,
    "ath_date": "2021-03-13T08:04:21.200Z",
    "atl": 0.00410887,
    "atl_change_percentage": 3586.03891,
    "atl_date": "2019-09-28T00:00:00.000Z",
    "roi": {
      "times": 5.8650367969627455,
      "currency": "usd",
      "percentage": 586.5036796962745
    },
    "last_updated": "2024-03-26T11:15:00.768Z"
  },
  {
    "id": "tezos",
    "symbol": "xtz",
    "name": "Tezos",
    "image": "https://assets.coingecko.com/coins/images/976/large/Tezos-logo.png?1696502091",
    "current_price": 1.38,
    "market_cap": 1344452159,
    "market_cap_rank": 89,
    "fully_diluted_valuation": 1372894350,
    "total_volume": 49676123,
    "high_24h": 1.38,
    "low_24h": 1.29,
    "price_change_24h": 0.075253,
    "price_change_percentage_24h": 5.78065,
    "market_cap_change_24h": 73721707,
    "market_cap_change_percentage_24h": 5.80152,
    "circulating_supply": 975797628.722768,
    "total_supply": 996440849.601022,
    "max_supply": null,
    "ath": 9.12,
    "ath_change_percentage": -84.85723,
    "ath_date": "2021-10-04T00:41:18.025Z",
    "atl": 0.350476,
    "atl_change_percentage": 293.87126,
    "atl_date": "2018-12-07T00:00:00.000Z",
    "roi": {
      "times": 1.929915831990566,
      "currency": "usd",
      "percentage": 192.9915831990566
    },
    "last_updated": "2024-03-26T11:15:37.007Z"
  },
  {
    "id": "ecash",
    "symbol": "xec",
    "name": "eCash",
    "image": "https://assets.coingecko.com/coins/images/16646/large/Logo_final-22.png?1696516207",
    "current_price": 6.907e-05,
    "market_cap": 1334595447,
    "market_cap_rank": 90,
    "fully_diluted_valuation": 1424665358,
    "total_volume": 40815345,
    "high_24h": 7.097e-05,
    "low_24h": 6.72e-05,
    "price_change_24h": 2.98312e-07,
    "price_change_percentage_24h": 0.43375,
    "market_cap_change_24h": -18176275.007656336,
    "market_cap_change_percentage_24h": -1.34363,
    "circulating_supply": 19672342173092.0,
    "total_supply": 21000000000000.0,
    "max_supply": 21000000000000.0,
    "ath": 0.00038001,
    "ath_change_percentage": -82.17564,
    "ath_date": "2021-09-04T17:09:31.137Z",
    "atl": 1.847e-05,
    "atl_change_percentage": 266.7312,
    "atl_date": "2021-07-20T20:49:46.212Z",
    "roi": null,
    "last_updated": "2024-03-26T11:16:19.578Z"
  },
  {
    "id": "ribbon-finance",
    "symbol": "rbn",
    "name": "Ribbon Finance",
    "image": "https://assets.coingecko.com/coins/images/15823/large/ribbon.png?1709186956",
    "current_price": 1.4,
    "market_cap": 1332794383,
    "market_cap_rank": 91,
    "fully_diluted_valuation": 1404373074,
    "total_volume": 9909991,
    "high_24h": 1.41,
    "low_24h": 1.34,
    "price_change_24h": 0.063589,
    "price_change_percentage_24h": 4.74346,
    "market_cap_change_24h": 62586984,
    "market_cap_change_percentage_24h": 4.9273,
    "circulating_supply": 949031569.534076,
    "total_supply": 1000000000.0,
    "max_supply": 1000000000.0,
    "ath": 5.54,
    "ath_change_percentage": -74.64736,
    "ath_date": "2021-10-07T22:30:49.258Z",
    "atl": 0.12452,
    "atl_change_percentage": 1028.32691,
    "atl_date": "2023-05-18T09:35:07.716Z",
    "roi": null,
    "last_updated": "2024-03-26T11:15:09.974Z"
  },
  {
    "id": "ethena-usde",
    "symbol": "usde",
    "name": "Ethena USDe",
    "image": "https://assets.coingecko.com/coins/images/33613/large/3466ef_3c088c66c7d941e8856339d0bddf33cc_mv2.png?1702514458",
    "current_price": 1.001,
    "market_cap": 1326633449,
    "market_cap_rank": 92,
    "fully_diluted_valuation": 1326633449,
    "total_volume": 52360123,
    "high_24h": 1.011,
    "low_24h": 0.992654,
    "price_change_24h": 0.00199172,
    "price_change_percentage_24h": 0.19945,
    "market_cap_change_24h": 15795057,
    "market_cap_change_percentage_24h": 1.20496,
    "circulating_supply": 1327571559.00506,
    "total_supply": 1327571559.00506,
    "max_supply": null,
    "ath": 1.032,
    "ath_change_percentage": -3.11321,
    "ath_date": "2023-12-20T15:38:34.596Z",
    "atl": 0.977814,
    "atl_change_percentage": 2.26399,
    "atl_date": "2024-01-09T21:19:32.385Z",
    "roi": null,
    "last_updated": "2024-03-26T11:15:43.186Z"
  },
  {
    "id": "bitget-token",
    "symbol": "bgb",
    "name": "Bitget Token",
    "image": "https://assets.coingecko.com/coins/images/11610/large/icon_colour.png?1696511504",
    "current_price": 0.938404,
    "market_cap": 1315703840,
    "market_cap_rank": 93,
    "fully_diluted_valuation": 1879575571,
    "total_volume": 38984378,
    "high_24h": 0.964842,
    "low_24h": 0.92575,
    "price_change_24h": -0.0102570084449779,
    "price_change_percentage_24h": -1.08121,
    "market_cap_change_24h": -12319110.341753483,
    "market_cap_change_percentage_24h": -0.92763,
    "circulating_supply": 1400001000.0,
    "total_supply": 2000000000.0,
    "max_supply": 2000000000.0,
    "ath": 1.15,
    "ath_change_percentage": -18.04667,
    "ath_date": "2024-02-17T06:30:15.580Z",
    "atl": 0.0142795,
    "atl_change_percentage": 6509.30061,
    "atl_date": "2020-06-25T04:17:05.895Z",
    "roi": null,
    "last_updated": "2024-03-26T11:14:52.826Z"
  },
  {
    "id": "ronin",
    "symbol": "ron",
    "name": "Ronin",
    "image": "https://assets.coingecko.com/coins/images/20009/large/Ronin_Mark_Blue.png?1707125056",
    "current_price": 4.31,
    "market_cap": 1313685058,
    "market_cap_rank": 94,
    "fully_diluted_valuation": 4310965560,
    "total_volume": 58486969,
    "high_24h": 4.45,
    "low_24h": 4.03,
    "price_change_24h": 0.200014,
    "price_change_percentage_24h": 4.8724,
    "market_cap_change_24h": 66630270,
    "market_cap_change_percentage_24h": 5.34301,
    "circulating_supply": 304731049.193701,
    "total_supply": 1000000000.0,
    "max_supply": 1000000000.0,
    "ath": 4.45,
    "ath_change_percentage": -3.30435,
    "ath_date": "2024-03-26T05:12:38.487Z",
    "atl": 0.196601,
    "atl_change_percentage": 2088.98342,
    "atl_date": "2022-11-21T19:36:31.487Z",
    "roi": null,
    "last_updated": "2024-03-26T11:15:21.260Z"
  },
  {
    "id": "akash-network",
    "symbol": "akt",
    "name": "Akash Network",
    "image": "https://assets.coingecko.com/coins/images/12785/large/akash-logo.png?1696512580",
    "current_price": 5.7,
    "market_cap": 1312769474,
    "market_cap_rank": 95,
    "fully_diluted_valuation": 1315078271,
    "total_volume": 10293679,
    "high_24h": 5.96,
    "low_24h": 5.58,
    "price_change_24h": 0.087941,
    "price_change_percentage_24h": 1.56797,
    "market_cap_change_24h": 17586691,
    "market_cap_change_percentage_24h": 1.35785,
    "circulating_supply": 231178955.161457,
    "total_supply": 231585534.716275,
    "max_supply": 388539008.0,
    "ath": 8.07,
    "ath_change_percentage": -29.22421,
    "ath_date": "2021-04-06T18:59:48.484Z",
    "atl": 0.164994,
    "atl_change_percentage": 3363.83911,
    "atl_date": "2022-11-21T20:30:53.727Z",
    "roi": null,
    "last_updated": "2024-03-26T11:15:47.679Z"
  },
  {
    "id": "ondo-finance",
    "symbol": "ondo",
    "name": "Ondo",
    "image": "https://assets.coingecko.com/coins/images/26580/large/ONDO.png?1696525656",
    "current_price": 0.906482,
    "market_cap": 1307439708,
    "market_cap_rank": 96,
    "fully_diluted_valuation": 9055767071,
    "total_volume": 384662356,
    "high_24h": 0.99338,
    "low_24h": 0.869801,
    "price_change_24h": 0.01056629,
    "price_change_percentage_24h": 1.17938,
    "market_cap_change_24h": 18304781,
    "market_cap_change_percentage_24h": 1.41993,
    "circulating_supply": 1443764727.588207,
    "total_supply": 10000000000.0,
    "max_supply": 10000000000.0,
    "ath": 0.99338,
    "ath_change_percentage": -7.98832,
    "ath_date": "2024-03-26T05:44:37.323Z",
    "atl": 0.082171,
    "atl_change_percentage": 1012.34566,
    "atl_date": "2024-01-18T12:14:30.524Z",
    "roi": null,
    "last_updated": "2024-03-26T11:16:23.961Z"
  },
  {
    "id": "apecoin",
    "symbol": "ape",
    "name": "ApeCoin",
    "image": "https://assets.coingecko.com/coins/images/24383/large/apecoin.jpg?1696523566",
    "current_price": 2.12,
    "market_cap": 1296715143,
    "market_cap_rank": 97,
    "fully_diluted_valuation": 2117986454,
    "total_volume": 103231728,
    "high_24h": 2.14,
    "low_24h": 2.0,
    "price_change_24h": 0.091888,
    "price_change_percentage_24h": 4.54007,
    "market_cap_change_24h": 56521854,
    "market_cap_change_percentage_24h": 4.5575,
    "circulating_supply": 612239583.0,
    "total_supply": 1000000000.0,
    "max_supply": 1000000000.0,
    "ath": 26.7,
    "ath_change_percentage": -92.05756,
    "ath_date": "2022-04-28T21:44:21.164Z",
    "atl": 1.008,
    "atl_change_percentage": 110.44077,
    "atl_date": "2023-10-10T20:51:07.411Z",
    "roi": null,
    "last_updated": "2024-03-26T11:16:01.521Z"
  },
  {
    "id": "decentraland",
    "symbol": "mana",
    "name": "Decentraland",
    "image": "https://assets.coingecko.com/coins/images/878/large/decentraland-mana.png?1696502010",
    "current_price": 0.689408,
    "market_cap": 1287753202,
    "market_cap_rank": 98,
    "fully_diluted_valuation": 1515048234,
    "total_volume": 134664057,
    "high_24h": 0.691307,
    "low_24h": 0.643592,
    "price_change_24h": 0.03685019,
    "price_change_percentage_24h": 5.64704,
    "market_cap_change_24h": 70378566,
    "market_cap_change_percentage_24h": 5.78118,
    "circulating_supply": 1864147713.459234,
    "total_supply": 2193179327.32015,
    "max_supply": 2193179327.32015,
    "ath": 5.85,
    "ath_change_percentage": -88.19701,
    "ath_date": "2021-11-25T10:04:18.534Z",
    "atl": 0.00923681,
    "atl_change_percentage": 7376.30572,
    "atl_date": "2017-10-31T00:00:00.000Z",
    "roi": {
      "times": 33.470413343116775,
      "currency": "usd",
      "percentage": 3347.0413343116775
    },
    "last_updated": "2024-03-26T11:15:07.685Z"
  },
  {
    "id": "eos",
    "symbol": "eos",
    "name": "EOS",
    "image": "https://assets.coingecko.com/coins/images/738/large/eos-eos-logo.png?1696501893",
    "current_price": 1.094,
    "market_cap": 1251798621,
    "market_cap_rank": 99,
    "fully_diluted_valuation": null,
    "total_volume": 165880162,
    "high_24h": 1.1,
    "low_24h": 1.042,
    "price_change_24h": 0.04520154,
    "price_change_percentage_24h": 4.30948,
    "market_cap_change_24h": 51096217,
    "market_cap_change_percentage_24h": 4.25553,
    "circulating_supply": 1144204156.3977,
    "total_supply": null,
    "max_supply": null,
    "ath": 22.71,
    "ath_change_percentage": -95.17731,
    "ath_date": "2018-04-29T07:50:33.540Z",
    "atl": 0.5024,
    "atl_change_percentage": 118.0123,
    "atl_date": "2017-10-23T00:00:00.000Z",
    "roi": {
      "times": 0.10513790661240101,
      "currency": "usd",
      "percentage": 10.513790661240101
    },
    "last_updated": "2024-03-26T11:15:51.513Z"
  },
  {
    "id": "tokenize-xchange",
    "symbol": "tkx",
    "name": "Tokenize Xchange",
    "image": "https://assets.coingecko.com/coins/images/4984/large/TKX_-_Logo_-_RGB-15.png?1696505519",
    "current_price": 15.37,
    "market_cap": 1229735531,
    "market_cap_rank": 100,
    "fully_diluted_valuation": 1537246278,
    "total_volume": 62404419,
    "high_24h": 15.46,
    "low_24h": 15.04,
    "price_change_24h": 0.336441,
    "price_change_percentage_24h": 2.2376,
    "market_cap_change_24h": 27280358,
    "market_cap_change_percentage_24h": 2.26872,
    "circulating_supply": 79995999.94518414,
    "total_supply": 100000000.0,
    "max_supply": 100000000.0,
    "ath": 22.3,
    "ath_change_percentage": -31.05927,
    "ath_date": "2022-10-31T10:23:59.455Z",
    "atl": 0.111255,
    "atl_change_percentage": 13716.21409,
    "atl_date": "2019-04-28T00:00:00.000Z",
    "roi": {
      "times": 51.91649174035191,
      "currency": "usd",
      "percentage": 5191.649174035191
    },
    "last_updated": "2024-03-26T11:15:30.774Z"
  }
]
